<?xml version="1.0" encoding="UTF-8"?><?ish ishref="GUID-9CBDAD12-FC22-4E9B-985F-2F49AF46DA85" version="3" lang="en-US"?><task xmlns:ditaarch="http://dita.oasis-open.org/architecture/2005/" id="GUID-9CBDAD12-FC22-4E9B-985F-2F49AF46DA85" xml:lang="en-US" ditaarch:DITAArchVersion="1.3" domains="(topic task)                            (topic hi-d)                            (topic ui-d)                            (topic sw-d)                            (topic indexing-d)                            (topic ut-d)                            a(base ishcondition)                            a(base varid)                            a(base varref)                            a(base cid)                            a(base partslist)                            (topic oce-d)                            (topic sdlVariables-c)                            (topic oceCommonElements-c)                            (topic oceMetaDecl-c)                            (topic oceTopic-c)                            (topic oceTopic-c task oceTask-c)                            (topic oceTopic-c hi-d oceHighlight-c)                            (topic oceTopic-c ui-d oceUi-c)                            (topic oceTopic-c sw-d oceSoftware-c)   " class="- topic/topic task/task "><title class="- topic/title "> Overview of the system installation (upto R4.3)</title><abstract class="- topic/abstract " id="M148553-B105"><p class="- topic/p ">This document gives an overview of the installation procedure. 
</p></abstract><prolog class="- topic/prolog "><metadata class="- topic/metadata "><category class="- topic/category ">Installation</category></metadata></prolog><taskbody class="- topic/body task/taskbody "><prereq id="M148553-B106" class="- topic/section task/prereq "><ol id="OL_65FCAD07281A4374B760FAB0797E9652" class="- topic/ol "><li id="LI_8D4654E109714EE49EBD0F809E60DB5E" class="- topic/li "><p class="- topic/p ">Use the information of the Site Preparation Guide to do a complete installation. 
</p></li><li class="- topic/li "><p class="- topic/p ">For Germany only: Check if a hard copy of the Operation guide is available for the customer in German. 
</p><p class="- topic/p ">If not, download and print the Operation guide. See: 
<xref keyref="ExtOperationGuide" class="- topic/xref " href="GUID-250A5CF0-B4FF-4B2C-B7C2-66A319226098.xml" format="dita" locktitle="yes" type="reference"><?ditaot usertext?><?xm-replace_text Operation and Safety information?>Operation and Safety information</xref> 
</p></li></ol><ul id="UL_013847E0D1814542B0D60FC899A26D92" class="- topic/ul "><li id="LI_FB64D446C5194C618F979D0E0507F42E" class="- topic/li "><note id="GUID-7FE07F3B-4488-4731-B962-6C7CF4403810" class="- topic/note "><p class="- topic/p ">Serial number, MAC address and software version (<ph translate="no" class="- topic/ph ">SWR</ph>) are on the sticker of the crate or on the top cover. 
</p><p class="- topic/p ">Based on the software version, you have to decide if you have to upgrade the firmware later on. 
</p></note><fig id="GUID-7C2E08C8-798F-4396-BC60-469692403D4C" class="- topic/fig "><title class="- topic/title ">Sticker with serial number on crate. </title><image href="GUID-1743063F-E926-4DE7-B395-E58EAFEDD85E-low.png" keyref="" placement="inline" class="- topic/image " otherprops="GUID-1743063F-E926-4DE7-B395-E58EAFEDD85E-low.png"/></fig><fig id="GUID-AA409A72-02D7-4E5F-9665-511058D878C5" class="- topic/fig "><title class="- topic/title ">Sticker with serial number, MAC address and software version on crate.</title><image href="GUID-8AB21E97-6E5F-4E68-8E9A-52557A4C483F-low.png" keyref="" placement="inline" class="- topic/image " otherprops="GUID-8AB21E97-6E5F-4E68-8E9A-52557A4C483F-low.png"/></fig><fig id="GUID-5EDB71C9-E65E-41BC-9016-C07255CAC7D6" class="- topic/fig "><title class="- topic/title ">Sticker with serial number, MAC address and software version on protection plastic of the top cover.</title><image href="GUID-A4E26F68-7C79-42CA-A990-D05CDC5031DC-low.png" keyref="" placement="inline" class="- topic/image " otherprops="GUID-A4E26F68-7C79-42CA-A990-D05CDC5031DC-low.png"/></fig></li></ul></prereq><section id="GUID-7559EFDE-78AF-4C15-810F-3DC4AF34D8C6" class="- topic/section "><title class="- topic/title ">Unpack</title><table id="TABLE_9811772F203F410B9A68CF17D0402387" pgwide="1" class="- topic/table "><tgroup align="left" outputclass="step" cols="3" class="- topic/tgroup "><colspec colname="col1" colnum="1" colwidth="10*" class="- topic/colspec "/><colspec colname="col2" colnum="2" colwidth="50*" class="- topic/colspec "/><colspec colname="col3" colnum="3" colwidth="40*" class="- topic/colspec "/><thead valign="top" class="- topic/thead "><row class="- topic/row "><entry colname="col1" align="left" valign="top" class="- topic/entry "><p class="- topic/p ">Step 
</p></entry><entry colname="col2" align="left" valign="top" class="- topic/entry "><p class="- topic/p ">Action 
</p></entry><entry colname="col3" align="left" valign="top" class="- topic/entry "><p class="- topic/p ">Remarks 
</p></entry></row></thead><tbody valign="top" class="- topic/tbody "><row class="- topic/row "><entry colname="col1" align="left" valign="top" class="- topic/entry "><p class="- topic/p ">1 
</p></entry><entry colname="col2" align="left" valign="top" class="- topic/entry "><p class="- topic/p ">Preparations: 
</p><ul id="UL_7052E04749824CE7BA53508C98ED8848" class="- topic/ul "><li id="LI_E29CBEA033A84375A318E5516687D748" class="- topic/li "><p class="- topic/p "><xref keyref="ENGINST04" class="- topic/xref " href="GUID-B1F7465C-0101-41F9-943E-640812B84974.xml" format="dita" locktitle="yes" type="task"><?ditaot usertext?><?xm-replace_text Dimension and weight of the crate?>Dimension and weight of the crate</xref> 
</p></li><li id="LI_6A623F5BB60D458CB0367027286F0F7B" class="- topic/li "><p class="- topic/p "><xref keyref="Printerdimension001" class="- topic/xref " href="GUID-01BC8361-BFAB-4CFF-B6F3-063EE47E4FE6.xml" format="dita" locktitle="yes" type="reference"><?ditaot usertext?><?xm-replace_text Printer dimensions?>Printer dimensions</xref> 
</p></li><li id="LI_731A7E7E66B64EB29D33AB90D390EF2B" class="- topic/li "><p class="- topic/p "><xref keyref="SpecFloorSpace" class="- topic/xref " href="GUID-C80191EB-B171-45F7-AB3D-CFDA08574B59.xml" format="dita" locktitle="yes" type="reference"><?ditaot usertext?><?xm-replace_text Floor space requirements?>Floor space requirements</xref> 
</p></li></ul></entry><entry colname="col3" align="left" valign="top" class="- topic/entry "/></row><row class="- topic/row "><entry colname="col1" align="left" valign="top" class="- topic/entry "><p class="- topic/p ">2 
</p></entry><entry colname="col2" align="left" valign="top" class="- topic/entry "><p class="- topic/p ">Unpack the printer. 
</p><p class="- topic/p ">See 
<xref keyref="ENGINST02" class="- topic/xref " href="GUID-EC9DCDAE-FC80-4BF9-8B65-2612AF54E279.xml" format="dita" locktitle="yes" type="task"><?ditaot usertext?><?xm-replace_text How to unpack the printer?>How to unpack the printer</xref>. 
</p></entry><entry colname="col3" align="left" valign="top" class="- topic/entry "/></row><row class="- topic/row "><entry colname="col1" align="left" valign="top" class="- topic/entry "><p class="- topic/p ">3 
</p></entry><entry colname="col2" align="left" valign="top" class="- topic/entry "><p class="- topic/p "> Place the printer 
<b class="+ topic/ph hi-d/b ">and</b> all other parts delivered with the system on the final location. 
</p></entry><entry colname="col3" align="left" valign="top" class="- topic/entry "/></row></tbody></tgroup></table></section><section id="GUID-C93DA330-2E35-4984-AF8E-D4C2F62BE7F7" class="- topic/section "><title class="- topic/title ">Finalize the printer</title><p class="- topic/p ">Video: 
<xref href="http://localhost:20346/VIDEO00394EN.US/video09/index.html" format="html" scope="external" class="- topic/xref "><?ditaot usertext?>How to install the Printer</xref> 
</p><table id="M148553-TB97" pgwide="1" class="- topic/table "><tgroup align="left" outputclass="step" cols="3" class="- topic/tgroup "><colspec colname="col1" colnum="1" colwidth="10*" class="- topic/colspec "/><colspec colname="col2" colnum="2" colwidth="50*" class="- topic/colspec "/><colspec colname="col3" colnum="3" colwidth="40*" class="- topic/colspec "/><thead valign="top" class="- topic/thead "><row class="- topic/row "><entry colname="col1" align="left" valign="top" class="- topic/entry "><p class="- topic/p ">Step 
</p></entry><entry colname="col2" align="left" valign="top" class="- topic/entry "><p class="- topic/p ">Action 
</p></entry><entry colname="col3" align="left" valign="top" class="- topic/entry "><p class="- topic/p ">Remarks 
</p></entry></row></thead><tbody valign="top" class="- topic/tbody "><row class="- topic/row "><entry colname="col1" align="left" valign="top" class="- topic/entry "><p class="- topic/p ">1 
</p></entry><entry colname="col2" align="left" valign="top" class="- topic/entry "><p class="- topic/p ">Check if all parts for the installation are available: 
</p><p class="- topic/p ">See: 
<xref keyref="INSTGEN003" class="- topic/xref " href="GUID-900A2F96-0CD4-4327-B3D3-4D9A374E17DA.xml" format="dita" locktitle="yes" type="concept"><?ditaot usertext?><?xm-replace_text Overview of the installation components and parts.?>Overview of the installation components and parts.</xref> 
</p></entry><entry colname="col3" align="left" valign="top" class="- topic/entry "/></row><row class="- topic/row "><entry colname="col1" align="left" valign="top" class="- topic/entry "><p class="- topic/p ">2 
</p></entry><entry colname="col2" align="left" valign="top" class="- topic/entry "><p class="- topic/p ">Remove the transport locking material from the printer. 
</p><p class="- topic/p ">see: 
<xref keyref="ENGINST03" class="- topic/xref " href="GUID-2C891C9E-77F8-4CF4-B85D-F15BEE655BDF.xml" format="dita" locktitle="yes" type="task"><?ditaot usertext?><?xm-replace_text Remove the transport locking material from the printer?>Remove the transport locking material from the printer</xref> 
</p></entry><entry colname="col3" align="left" valign="top" class="- topic/entry "/></row><row class="- topic/row "><entry colname="col1" align="left" valign="top" class="- topic/entry "><p class="- topic/p ">3 
</p></entry><entry colname="col2" align="left" valign="top" class="- topic/entry "><p class="- topic/p "> Prepare the ink pumps for CMYK or CMYKW configuration. 
</p><p class="- topic/p ">See: 
<xref href="GUID-87BCE552-1B5E-4609-B104-F83697F46FF3.xml" scope="local" format="dita" class="- topic/xref " type="task"><?ditaot gentext?>02 How to install and grease the pump tubes</xref> 
</p></entry><entry colname="col3" align="left" valign="top" class="- topic/entry "><note id="GUID-F4161B5C-1DE2-4CA1-A80D-AB97AEBB2FA8" class="- topic/note "><p class="- topic/p ">When not installing White, do 
<b class="+ topic/ph hi-d/b ">not</b> grease the white ink pump and keep the pump tube 
<b class="+ topic/ph hi-d/b ">out of the pump</b>. 
</p></note><note id="GUID-DE441065-4007-46DD-9509-7EF7FD83DD66" class="- topic/note "><p class="- topic/p ">Keep the not used grease with the printer. Upgrade to white will require the grease. 
</p></note></entry></row><row class="- topic/row "><entry colname="col1" align="left" valign="top" class="- topic/entry "><p class="- topic/p ">4 
</p></entry><entry colname="col2" align="left" valign="top" class="- topic/entry "><p class="- topic/p ">Install Aerosol Ink Filter Units. 
</p><p class="- topic/p ">See: 
<xref keyref="05INSTMODKITMIST" class="- topic/xref " href="GUID-90C9CBD9-2EA5-416E-9AF5-2F7B5C3CCA06.xml" format="dita" locktitle="yes" type="task"><?ditaot usertext?><?xm-replace_text 05 How install the Modification kit of the Aerosol Ink Filter Units...?>05 How install the Modification kit of the Aerosol Ink Filter Units (mod 01)</xref> 
</p></entry><entry colname="col3" align="left" valign="top" class="- topic/entry "><p class="- topic/p ">MOD01 
</p></entry></row><row class="- topic/row "><entry colname="col1" align="left" valign="top" class="- topic/entry "><p class="- topic/p ">5 
</p></entry><entry colname="col2" align="left" valign="top" class="- topic/entry "><p class="- topic/p ">Install the filters or external exhaust: 
</p><p class="- topic/p ">Do 
<xref keyref="24Install001" class="- topic/xref " href="GUID-AC604C6C-F75C-49CE-802D-16B819549D30.xml" format="dita" locktitle="yes" type="task"><?ditaot usertext?><?xm-replace_text 24 How to install the Frame filters?>24 How to install the Frame filters</xref> 
</p><p class="- topic/p ">or 
</p><p class="- topic/p ">Do 
<xref keyref="24Install002" class="- topic/xref " href="GUID-C6929516-4D3F-4BCB-8B58-4E45EA2322B9.xml" format="dita" locktitle="yes" type="task"><?ditaot usertext?><?xm-replace_text 24 How to install the exhaust?>24 How to install the exhaust</xref> 
</p></entry><entry colname="col3" align="left" valign="top" class="- topic/entry "/></row><row class="- topic/row "><entry colname="col1" align="left" valign="top" class="- topic/entry "><p class="- topic/p ">6 
</p></entry><entry colname="col2" align="left" valign="top" class="- topic/entry "><p class="- topic/p ">Level the printer and adjust the winder. 
</p><p class="- topic/p ">See 
<xref keyref="ENGADJU01" class="- topic/xref " href="GUID-2BFE3033-C726-47A1-9A09-044CAA7F04FE.xml" format="dita" locktitle="yes" type="task"><?ditaot usertext?><?xm-replace_text 00 How to level the printer?>00 How to level the printer</xref>. 
</p><p class="- topic/p ">See 
<xref keyref="19ADJU002" class="- topic/xref " href="GUID-D7027CEA-D5AB-4EDB-A8A6-C62E98486F84.xml" format="dita" locktitle="yes" type="task"><?ditaot usertext?><?xm-replace_text 19 How to adjust the winder with respect to the printer?>19 How to adjust the winder with respect to the printer</xref> 
</p></entry><entry colname="col3" align="left" valign="top" class="- topic/entry "/></row><row class="- topic/row "><entry colname="col1" align="left" valign="top" class="- topic/entry "><p class="- topic/p ">7 
</p></entry><entry colname="col2" align="left" valign="top" class="- topic/entry "><p class="- topic/p ">Install the user panel. 
</p><p class="- topic/p ">See 
<xref keyref="ENGGENINSTUSERPANEL001" class="- topic/xref " href="GUID-66DA01A7-3214-4E75-8AD4-489533703FF8.xml" format="dita" locktitle="yes" type="task"><?ditaot usertext?><?xm-replace_text Install the operator panel?>Install the operator panel</xref> 
</p></entry><entry colname="col3" align="left" valign="top" class="- topic/entry "/></row><row class="- topic/row "><entry colname="col1" align="left" valign="top" class="- topic/entry "><p class="- topic/p ">8 
</p></entry><entry colname="col2" align="left" valign="top" class="- topic/entry "><p class="- topic/p ">Install Optional units 
</p></entry><entry colname="col3" align="left" valign="top" class="- topic/entry "><ul class="- topic/ul "><li class="- topic/li "><p class="- topic/p ">JUMBO-roll 
</p><p class="- topic/p ">See: 
<xref keyref="12INSTJUMBOROLL" class="- topic/xref " href="GUID-69C93470-DBBC-48E8-9996-99D50028E362.xml" format="dita" locktitle="yes" type="task"><?ditaot usertext?><?xm-replace_text 12 How to install and configure the Interface unit for the Jumbo...?>12 How to install and configure the Interface unit for the Jumbo Roll Unit</xref> 
</p></li><li class="- topic/li "><p class="- topic/p ">Magnetic Media Kit 
</p></li></ul><p class="- topic/p ">See: 
<xref keyref="12INSTMAGNMEDIAKIT" class="- topic/xref " href="GUID-1174A86D-1235-4BBA-AD2A-9F46ACE56AB8.xml" format="dita" locktitle="yes" type="task"><?ditaot usertext?><?xm-replace_text 12 How to install the Magnetic Media Kit?>12 How to install the Magnetic Media Kit</xref> 
</p></entry></row><row class="- topic/row "><entry colname="col1" align="left" valign="top" class="- topic/entry "><p class="- topic/p ">9 
</p></entry><entry colname="col2" align="left" valign="top" class="- topic/entry "><p class="- topic/p ">Install/configure 
</p></entry><entry colname="col3" align="left" valign="top" class="- topic/entry "><ul class="- topic/ul "><li class="- topic/li "><p class="- topic/p ">Print inside Winding functionality. 
</p><p class="- topic/p ">Install the appropriate license. 
</p></li><li class="- topic/li "><p class="- topic/p ">Interface unit for JUMBO Roll unit. 
</p><p class="- topic/p ">See: 
<xref keyref="12INSTJUMBOROLL" class="- topic/xref " href="GUID-69C93470-DBBC-48E8-9996-99D50028E362.xml" format="dita" locktitle="yes" type="task"><?ditaot usertext?><?xm-replace_text 12 How to install and configure the Interface unit for the Jumbo...?>12 How to install and configure the Interface unit for the Jumbo Roll Unit</xref> 
</p></li></ul></entry></row><row class="- topic/row "><entry colname="col1" align="left" valign="top" class="- topic/entry "><p class="- topic/p ">10 
</p></entry><entry colname="col2" align="left" valign="top" class="- topic/entry "><p class="- topic/p ">Adjust the top cover door switches (24S1 and 24S5) 
</p><p class="- topic/p ">See: 
<xref keyref="24ADJU003" class="- topic/xref " href="GUID-D21117EB-3577-4323-8C37-CD7715B9EC83.xml" format="dita" locktitle="yes" type="task"><?ditaot usertext?><?xm-replace_text 24 How to adjust the top cover door switches (24S1 and 24S5)?>24 How to adjust the top cover door switches (24S1 and 24S5)</xref> 
</p></entry><entry colname="col3" align="left" valign="top" class="- topic/entry "/></row><row class="- topic/row "><entry colname="col1" align="left" valign="top" class="- topic/entry "><p class="- topic/p ">11 
</p></entry><entry colname="col2" align="left" valign="top" class="- topic/entry "><p class="- topic/p "> Verify the strip support 
</p></entry><entry colname="col3" align="left" valign="top" class="- topic/entry "><p class="- topic/p "> Manually move the printhead carriage with a more or less continuous speed from left to right and back. 
</p><p class="- topic/p ">The top of the metal strip should remain at approximately ( within 10 mm) the same height. 
</p><p class="- topic/p "> Adjustment is necessary to prevent the strip support touching and damaging the top cover. 
</p><p class="- topic/p ">Execute the procedure<xref href="GUID-C363DEF6-7E13-4C80-853C-77BAC2CB529E.xml" scope="local" format="dita" class="- topic/xref " type="task"><?ditaot gentext?>05 How to adjust the strip support (to avoid bouncing)</xref> 
</p></entry></row><row class="- topic/row "><entry colname="col1" align="left" valign="top" class="- topic/entry "><p class="- topic/p ">12 
</p></entry><entry colname="col2" align="left" valign="top" class="- topic/entry "><p class="- topic/p ">Install the chiller 
</p><p class="- topic/p ">see: 
<xref keyref="installchiller" class="- topic/xref " href="GUID-260E8B4D-A641-48EF-84A7-7344BE9CE5EC.xml" format="dita" locktitle="yes" type="task"><?ditaot usertext?><?xm-replace_text 06 How to install the chiller (V2)?>06 How to install the chiller (V2)</xref> 
</p></entry><entry colname="col3" align="left" valign="top" class="- topic/entry "><note id="GUID-CCDD675C-7566-4C52-ADC8-A41EC8A79A22" class="- topic/note "><p class="- topic/p ">Do not exceed the maximum of the full rang. 
</p><p class="- topic/p ">Fill first 6 bottles and when engine is going to standby, the last 2-3 bottles 
</p></note></entry></row><row class="- topic/row "><entry colname="col1" align="left" valign="top" class="- topic/entry "><p class="- topic/p ">13 
</p></entry><entry colname="col2" align="left" valign="top" class="- topic/entry "><p class="- topic/p "> Install the printheads and dummy printheads (including the service jumper). 
</p><p class="- topic/p ">See 
<xref keyref="04INST001" class="- topic/xref " href="GUID-2388CE18-EA64-412B-9157-B31DB3FD34CE.xml" format="dita" locktitle="yes" type="task"><?ditaot usertext?><?xm-replace_text 04 How to install the printheads?>04 How to install the printheads</xref>. 
</p></entry><entry colname="col3" align="left" valign="top" class="- topic/entry "><note id="GUID-1FFFEB7F-A514-467B-A6F1-6E7EAB08A865" class="- topic/note "><ul class="- topic/ul "><li class="- topic/li "><p class="- topic/p ">In case of a CMYK installation, 1 printhead flex cable will be left over. This needs to be stored in the printer. 
</p></li><li class="- topic/li "><p class="- topic/p "> In case of a CMYKW installation, the dummy printhead of pos1 and its "plug air duct" needs to be stored with the printer in the service box. 
</p></li></ul><p class="- topic/p ">Keep the blisters and caps with the printer. 
</p></note></entry></row><row class="- topic/row "><entry colname="col1" align="left" valign="top" class="- topic/entry "><p class="- topic/p ">14 
</p></entry><entry colname="col2" align="left" valign="top" class="- topic/entry "><p class="- topic/p ">Check if the power switch is in the OFF position. 
</p></entry><entry colname="col3" align="left" valign="top" class="- topic/entry "><fig id="GUID-E926793B-ED8D-45CD-ABA8-E217E11F9279" class="- topic/fig "><image href="GUID-893A9144-40E2-452E-AE68-3C30E1DCC612-low.png" keyref="" placement="inline" class="- topic/image " otherprops="GUID-893A9144-40E2-452E-AE68-3C30E1DCC612-low.png"/></fig></entry></row><row class="- topic/row "><entry colname="col1" align="left" valign="top" class="- topic/entry "><p class="- topic/p ">15 
</p></entry><entry colname="col2" align="left" valign="top" class="- topic/entry "><p class="- topic/p ">Place Tissue Wipe cassette. 
</p></entry><entry colname="col3" align="left" valign="top" class="- topic/entry "><p class="- topic/p "><xref keyref="Replace_the_tissue_cassette" class="- topic/xref " href="GUID-0CC64B23-BFB9-4235-A901-5C82E5BEBC85.xml" format="dita" locktitle="yes" type="task"><?ditaot usertext?><?xm-replace_text Replace the tissue cassette?>Replace the tissue cassette</xref> 
</p></entry></row><row class="- topic/row "><entry colname="col1" align="left" valign="top" class="- topic/entry "><p class="- topic/p ">16 
</p></entry><entry colname="col2" align="left" valign="top" class="- topic/entry "><p class="- topic/p ">Place the bag with 
</p><ul class="- topic/ul "><li class="- topic/li "><p class="- topic/p ">All caps of the ink tubes 
</p></li><li class="- topic/li "><p class="- topic/p ">All caps of the air tubes 
</p></li><li class="- topic/li "><p class="- topic/p ">the 2 protection caps of the glass fiber cable 
</p></li><li class="- topic/li "><p class="- topic/p ">Printhead Flat cable (in case Whit ink-option is not applied. 
</p></li><li class="- topic/li "><p class="- topic/p "> Dummy printhead (in case White ink option installed) 
</p></li><li class="- topic/li "><p class="- topic/p ">Plug Air Duct (in case White ink option installed) 
</p></li></ul><p class="- topic/p ">in the service box. 
</p></entry><entry colname="col3" align="left" valign="top" class="- topic/entry "><fig id="GUID-A87437A8-39E2-4E2D-A697-DEBFFD94C70E" class="- topic/fig "><image href="GUID-A271FA17-8354-4A5E-A815-D5F6593AF1C2-low.png" keyref="" placement="inline" class="- topic/image " otherprops="GUID-A271FA17-8354-4A5E-A815-D5F6593AF1C2-low.png"/></fig><fig id="GUID-52BCD5EA-E26A-4A93-A766-FF74EC55C0E9" class="- topic/fig "><image href="GUID-DD98158F-F935-4ECC-8DD6-AFB5D03DBFD8-low.png" keyref="" placement="inline" class="- topic/image " otherprops="GUID-DD98158F-F935-4ECC-8DD6-AFB5D03DBFD8-low.png"/></fig></entry></row><row class="- topic/row "><entry colname="col1" align="left" valign="top" class="- topic/entry "><p class="- topic/p ">17 
</p></entry><entry colname="col2" align="left" valign="top" class="- topic/entry "><p class="- topic/p ">Place the service box below the media drawer. 
</p></entry><entry colname="col3" align="left" valign="top" class="- topic/entry "><fig id="GUID-C64A6ECA-5A7F-40AA-AAA4-41D366C8E732" class="- topic/fig "><image href="GUID-BE9EE50D-FEEA-45D4-ADA9-DD02C5182CC8-low.png" keyref="" placement="inline" class="- topic/image " otherprops="GUID-BE9EE50D-FEEA-45D4-ADA9-DD02C5182CC8-low.png"/></fig></entry></row><row class="- topic/row "><entry colname="col1" align="left" valign="top" class="- topic/entry "><p class="- topic/p ">18 
</p></entry><entry colname="col2" align="left" valign="top" class="- topic/entry "><p class="- topic/p ">Mount the cover of the knife compartment. 
</p></entry><entry colname="col3" align="left" valign="top" class="- topic/entry "><fig id="GUID-BC7316F1-1F13-4838-BBC0-4C7BE3573B32" class="- topic/fig "><image href="GUID-E61666AA-9FAF-4C56-BA59-C79A31117DDF-low.png" keyref="" placement="inline" class="- topic/image " otherprops="GUID-E61666AA-9FAF-4C56-BA59-C79A31117DDF-low.png"/></fig></entry></row><row class="- topic/row "><entry colname="col1" align="left" valign="top" class="- topic/entry "><p class="- topic/p ">19 
</p></entry><entry colname="col2" align="left" valign="top" class="- topic/entry "><p class="- topic/p ">Configure the main voltage 
</p></entry><entry colname="col3" align="left" valign="top" class="- topic/entry "><p class="- topic/p ">How to adjust the voltage of the trafo box (V2) 
</p><p class="- topic/p ">see: 
<xref keyref="06ADJU001" class="- topic/xref " href="GUID-89EA44C7-2322-4626-BAAF-FC7D434979B6.xml" format="dita" locktitle="yes" type="task"><?ditaot usertext?><?xm-replace_text 06 How to adjust the voltage of the trafo box (V2)?>06 How to adjust the voltage of the trafo box (V2)</xref> 
</p></entry></row><row class="- topic/row "><entry colname="col1" align="left" valign="top" class="- topic/entry "><p class="- topic/p ">20 
</p></entry><entry colname="col2" align="left" valign="top" class="- topic/entry "><ol class="- topic/ol "><li class="- topic/li "><p class="- topic/p ">Open the lower cover. 
</p></li><li class="- topic/li "><p class="- topic/p ">Connect the 2 mains cables. 
</p><note type="caution" id="GUID-53F4ECBA-6AB4-414E-9D89-6A47AD99D5EE" class="- topic/note "><p class="- topic/p ">Use protective gloves if you guide the cables underneath the printer. 

</p></note></li></ol></entry><entry colname="col3" align="left" valign="top" class="- topic/entry "><fig id="GUID-0113CA00-43BC-4C20-A045-E87B7081AC9B" class="- topic/fig "><image href="GUID-9450E49C-5972-4CFA-B24E-D6BC1454DBFE-low.png" keyref="" placement="inline" class="- topic/image " otherprops="GUID-9450E49C-5972-4CFA-B24E-D6BC1454DBFE-low.png"/></fig></entry></row><row class="- topic/row "><entry colname="col1" align="left" valign="top" class="- topic/entry "><p class="- topic/p ">21 
</p></entry><entry colname="col2" align="left" valign="top" class="- topic/entry "><p class="- topic/p ">Connect the network cable. 
</p></entry><entry colname="col3" align="left" valign="top" class="- topic/entry "><fig id="GUID-F405E163-C4EF-4DBA-A99A-F5AB3DB1811C" class="- topic/fig "><image href="GUID-2DDBA917-F410-433B-8CF6-AC8BA3D365F6-low.png" keyref="" placement="inline" class="- topic/image " otherprops="GUID-2DDBA917-F410-433B-8CF6-AC8BA3D365F6-low.png"/></fig></entry></row><row class="- topic/row "><entry colname="col1" align="left" valign="top" class="- topic/entry "><p class="- topic/p ">22 
</p></entry><entry colname="col2" align="left" valign="top" class="- topic/entry "><p class="- topic/p ">Place the 2 rollers on the winder. 
</p></entry><entry colname="col3" align="left" valign="top" class="- topic/entry "><fig id="GUID-6234F2CA-58E5-4C72-B4FB-73301F8F769A" class="- topic/fig "><image href="GUID-EF3737E3-8421-40A0-AA85-69F763911131-low.png" keyref="" placement="inline" class="- topic/image " otherprops="GUID-EF3737E3-8421-40A0-AA85-69F763911131-low.png"/></fig><fig id="GUID-0B4462ED-57C9-4614-AEED-C2A3F50DBC34" class="- topic/fig "><image href="GUID-B0EBDBA8-80DD-4A17-9232-FE3AFB291B48-low.png" keyref="" placement="inline" class="- topic/image " otherprops="GUID-B0EBDBA8-80DD-4A17-9232-FE3AFB291B48-low.png"/></fig></entry></row></tbody></tgroup></table></section><section id="GUID-8AE2CBBA-E30A-4A17-B8C6-458E025F47BA" class="- topic/section "><title class="- topic/title ">Switch on / Software installation / Installation wizard / License request / Ink fill</title><p class="- topic/p "><b class="+ topic/ph hi-d/b ">If applicable: Upgrade the system to the latest available software version as described in the table below. 
</b> 
</p><note type="important" id="GUID-6ED9E33E-2B5C-47D0-A6B5-84A70FB8ADD1" class="- topic/note "><p class="- topic/p ">Depending on the firmware version of the User panel, a black screen might be shown for about 5 minutes. 
</p><p class="- topic/p ">Do 
<b class="+ topic/ph hi-d/b ">NOT</b> switch the machine off! This will damage the user panel since new firmware is being loaded. 
</p></note><table pgwide="1" id="GUID-CCE666FA-B63F-48A3-A8EB-70A2970EDEF4" class="- topic/table "><tgroup align="left" outputclass="step" cols="3" class="- topic/tgroup "><colspec colname="col1" colnum="1" colwidth="10*" class="- topic/colspec "/><colspec colname="col2" colnum="2" colwidth="50*" class="- topic/colspec "/><colspec colname="col3" colnum="3" colwidth="40*" class="- topic/colspec "/><thead valign="top" class="- topic/thead "><row class="- topic/row "><entry colname="col1" align="left" valign="top" class="- topic/entry "><p class="- topic/p ">Step 
</p></entry><entry colname="col2" align="left" valign="top" class="- topic/entry "><p class="- topic/p ">Action 
</p></entry><entry colname="col3" align="left" valign="top" class="- topic/entry "><p class="- topic/p ">Remarks 
</p></entry></row></thead><tbody valign="top" class="- topic/tbody "><row class="- topic/row "><entry colname="col1" align="left" valign="top" class="- topic/entry "><p class="- topic/p ">1 
</p></entry><entry colname="col2" align="left" valign="top" class="- topic/entry "><p class="- topic/p ">Insert the installation USB key in the printer (USB port below the operator panel). 
</p><p class="- topic/p ">See 
<xref keyref="20INST-USBKEY" class="- topic/xref " href="GUID-51DC0123-5924-4D7D-B345-F3B06B4B248C.xml" format="dita" locktitle="yes" type="task"><?ditaot usertext?><?xm-replace_text 11 How to create an installation USB Key?>11 How to create an installation USB Key</xref> 
</p></entry><entry colname="col3" align="left" valign="top" class="- topic/entry "><note id="GUID-EF2750B7-E37B-42B4-BAC1-804DD2BC258E" class="- topic/note "><p class="- topic/p "> Install with 'keep settings' set to 
<b class="+ topic/ph hi-d/b ">yes</b> during a system installation. 
</p></note></entry></row><row class="- topic/row "><entry colname="col1" align="left" valign="top" class="- topic/entry "><p class="- topic/p ">2 
</p></entry><entry colname="col2" align="left" valign="top" class="- topic/entry "><p class="- topic/p ">Switch the printer ON with the power switch (next to the power inlets). 
</p></entry><entry colname="col3" align="left" valign="top" class="- topic/entry "/></row><row class="- topic/row "><entry colname="col1" align="left" valign="top" class="- topic/entry "><p class="- topic/p ">3 
</p></entry><entry colname="col2" align="left" valign="top" class="- topic/entry "><p class="- topic/p ">The installation of the latest software version will start now. 
</p></entry><entry colname="col3" align="left" valign="top" class="- topic/entry "><p class="- topic/p ">This will take approximately 60 minutes. 
</p><note id="GUID-A720635F-9296-489C-826C-E1014BF63630" class="- topic/note "><p class="- topic/p ">Keep the covers closed. Opening a cover will stop the firmware upgrade. 
</p></note></entry></row><row class="- topic/row "><entry colname="col1" align="left" valign="top" class="- topic/entry "><p class="- topic/p ">4 
</p></entry><entry colname="col2" align="left" valign="top" class="- topic/entry "><p class="- topic/p ">After the Controller installation the printer will automatically start up. 
</p></entry><entry colname="col3" align="left" valign="top" class="- topic/entry "/></row><row class="- topic/row "><entry colname="col1" align="left" valign="top" class="- topic/entry "><p class="- topic/p ">5 
</p></entry><entry colname="col2" align="left" valign="top" class="- topic/entry "><p class="- topic/p ">Remove the installation USB key from the printer. 
</p></entry><entry colname="col3" align="left" valign="top" class="- topic/entry "/></row><row class="- topic/row "><entry colname="col1" align="left" valign="top" class="- topic/entry "><p class="- topic/p ">6 
</p></entry><entry colname="col2" align="left" valign="top" class="- topic/entry "><p class="- topic/p ">Follow the instructions in the installation wizard (Part 1) until the printer is rebooting. 
</p><p class="- topic/p ">see: 
<xref keyref="GININSTWIZZARD001" class="- topic/xref " href="GUID-36980814-B41B-4AFD-B05F-6D57C557C949.xml" format="dita" locktitle="yes" type="task"><?ditaot usertext?><?xm-replace_text Installation wizard (part 1) (upto R4.3)?>Installation wizard (part 1) (upto R4.3)</xref> 
</p><p class="- topic/p "> Embedded Firmware (FW) upgrades of the PBAs are done in parallel. In case the FW upgrades are still running, the reboot takes longer since the controller waits for the running FW upgrades to finish. This is indicated in the operator panel. 
</p><note id="GUID-41360699-6DAE-4803-9C3D-60F71E75308F" class="- topic/note "><p class="- topic/p ">Skip the license installation. 
</p></note></entry><entry colname="col3" align="left" valign="top" class="- topic/entry "><note id="GUID-4144AE66-5C55-4D64-9138-2A6F54F7390B" class="- topic/note "><p class="- topic/p "> If a machine recoverable Error (MRE) occurs during the install wizard, you might need to restart twice to get the install wizard back!! 
</p></note><note id="GUID-573B5489-BD97-4B36-BA02-D939CC26A180" class="- topic/note "><p class="- topic/p ">When the engine UI is displaying its content upside down: 
</p><ol class="- topic/ol "><li class="- topic/li "><p class="- topic/p ">restart the engine 
</p></li><li class="- topic/li "><p class="- topic/p ">disconnect the HDMI from the UI panel 
</p></li><li class="- topic/li "><p class="- topic/p ">wait until the power button is green 
</p></li><li class="- topic/li "><p class="- topic/p ">plug in the HDMI and continue 
</p></li></ol></note></entry></row><row class="- topic/row "><entry colname="col1" align="left" valign="top" class="- topic/entry "><p class="- topic/p ">7 
</p></entry><entry colname="col2" align="left" valign="top" class="- topic/entry "><p class="- topic/p ">Continue with the installation wizard (Part 2) on the operator panel. 
</p><p class="- topic/p "> When executing make sure you enable the remote service to be able to retrieve the license via ORS later. 
</p><p class="- topic/p ">See 
<xref keyref="GININSTWIZZARD002" class="- topic/xref " href="GUID-A79BBB14-8F14-4790-A7F4-30D204C55A0A.xml" format="dita" locktitle="yes" type="task"><?ditaot usertext?><?xm-replace_text Installation wizard (Part 2) (upto R4.3)?>Installation wizard (Part 2) (upto R4.3)</xref> 
</p></entry><entry colname="col3" align="left" valign="top" class="- topic/entry "><note id="GUID-55EF827C-1D5B-4EC0-B7C4-D53EA87D5CFE" class="- topic/note "><p class="- topic/p ">In case the system starts and asks for ink you must restart the system and finish the wizard first. This must be done before you load the ink bottles. 
</p></note></entry></row><row class="- topic/row "><entry colname="col1" align="left" valign="top" class="- topic/entry "><p class="- topic/p ">8 
</p></entry><entry colname="col2" align="left" valign="top" class="- topic/entry "><p class="- topic/p "> Access the printer 's web interface by means of a customer PC to retrieve the license information. 
</p><p class="- topic/p "> Request a license file for the system: 
</p><ul class="- topic/ul "><li class="- topic/li "><p class="- topic/p ">Request a license file for the system via ORS. 
</p><p class="- topic/p ">See: 
<xref keyref="AutoLicenseViaORS" class="- topic/xref " href="GUID-66521B0A-9EE4-432D-8C42-473926C9FB43.xml" format="dita" locktitle="yes" type="task"><?ditaot usertext?><?xm-replace_text How to request a license via ORS?>How to request a license via ORS</xref> 
</p></li><li class="- topic/li "><p class="- topic/p ">Alternative way of retrieving the license 
</p><p class="- topic/p ">See: 
<xref keyref="GENINSTALLLICENSE001" class="- topic/xref " href="GUID-83541379-2C72-4191-948E-292B66F16EE2.xml" format="dita" locktitle="yes" type="task"><?ditaot usertext?><?xm-replace_text How to request a license?>How to request a license</xref> 
</p></li></ul></entry><entry colname="col3" align="left" valign="top" class="- topic/entry "><note id="GUID-108EBE4B-5CD2-4952-ADB5-5CFDD3BF70B5" class="- topic/note "><p class="- topic/p "> Via ORS: Only execute the "Request the license" continue with the regular installation. Installation of the license can be after the calibrations. 
</p></note></entry></row></tbody></tgroup></table></section><section id="GUID-A42FED28-8C12-466D-B03E-671984900FE1" class="- topic/section "><title class="- topic/title "/><p class="- topic/p ">At this moment the machine has continued with booting the Embedded Controller. 
</p><p class="- topic/p "> As a consequence the engine will request for ink to be filled and will request the waste bin to be replaced. 
</p><p class="- topic/p "> Filling the ink tubes and the printheads with ink is starting now. 
</p></section><section id="GUID-94313385-1A2E-46BE-A57E-AB2A4A0210DF" class="- topic/section "><title class="- topic/title ">Enter SDS</title><table pgwide="1" id="GUID-ABA0CC54-F3D5-4063-9833-12FB96F3BBA5" class="- topic/table "><tgroup align="left" outputclass="step" cols="3" class="- topic/tgroup "><colspec colname="col1" colnum="1" colwidth="10*" class="- topic/colspec "/><colspec colname="col2" colnum="2" colwidth="50*" class="- topic/colspec "/><colspec colname="col3" colnum="3" colwidth="40*" class="- topic/colspec "/><thead valign="top" class="- topic/thead "><row class="- topic/row "><entry colname="col1" align="left" valign="top" class="- topic/entry "><p class="- topic/p ">Step 
</p></entry><entry colname="col2" align="left" valign="top" class="- topic/entry "><p class="- topic/p ">Action 
</p></entry><entry colname="col3" align="left" valign="top" class="- topic/entry "><p class="- topic/p ">Remarks 
</p></entry></row></thead><tbody valign="top" class="- topic/tbody "><row class="- topic/row "><entry colname="col1" align="left" valign="top" class="- topic/entry "><p class="- topic/p ">1 
</p></entry><entry colname="col2" align="left" valign="top" class="- topic/entry "><p class="- topic/p ">Insert the SAM key and start SDS 
</p><p class="- topic/p ">See : 
<xref keyref="SDS01" class="- topic/xref " href="GUID-60790B61-6280-4724-A0A6-9A9E00941745.xml" format="dita" locktitle="yes" type="task"><?ditaot usertext?><?xm-replace_text How to enter SDS?>How to enter SDS</xref>. 
</p></entry><entry colname="col3" align="left" valign="top" class="- topic/entry "/></row></tbody></tgroup></table></section><section id="GUID-E203C7C6-36F6-46B1-872C-44BEEF2F4623" class="- topic/section "><title class="- topic/title ">Set configuration filters (optional)</title><table id="GUID-CC9457B8-C190-4002-8192-C7110AF8958F" pgwide="1" class="- topic/table "><tgroup align="left" outputclass="step" cols="3" class="- topic/tgroup "><colspec colname="col1" colnum="1" colwidth="10*" class="- topic/colspec "/><colspec colname="col2" colnum="2" colwidth="50*" class="- topic/colspec "/><colspec colname="col3" colnum="3" colwidth="40*" class="- topic/colspec "/><thead valign="top" class="- topic/thead "><row class="- topic/row "><entry colname="col1" align="left" valign="top" class="- topic/entry "><p class="- topic/p ">Step 
</p></entry><entry colname="col2" align="left" valign="top" class="- topic/entry "><p class="- topic/p ">Action 
</p></entry><entry colname="col3" align="left" valign="top" class="- topic/entry "><p class="- topic/p ">Remarks 
</p></entry></row></thead><tbody valign="top" class="- topic/tbody "><row class="- topic/row "><entry colname="col1" align="left" valign="top" class="- topic/entry "><p class="- topic/p ">1 
</p></entry><entry colname="col2" align="left" valign="top" class="- topic/entry "><p class="- topic/p ">Optional: 
<b class="+ topic/ph hi-d/b ">only with external exhaust.</b> 
</p><p class="- topic/p ">Set the filters or external exhaust configuration: 
</p><p class="- topic/p ">Do 
<xref keyref="SDS24-1-001" class="- topic/xref " href="GUID-FF412B50-9595-4D6D-95B7-9B8DAC9763DF.xml" format="dita" locktitle="yes" type="task"><?ditaot usertext?><?xm-replace_text 24-1-001 Type of air filtering [Parameters]?>24-1-001 Type of air filtering [Parameters]</xref>. 
</p><p class="- topic/p "> Set the correct configuration (Default: Filters available). 
</p></entry><entry colname="col3" align="left" valign="top" class="- topic/entry "/></row></tbody></tgroup></table></section><section id="GUID-8193CE86-66C1-4A41-9766-B0028406C89D" class="- topic/section "><title class="- topic/title ">Set configuration White (optional)</title><table pgwide="1" id="GUID-EB4DEEE2-D94A-4C8E-ACFC-E7B8904A6509" class="- topic/table "><tgroup align="left" outputclass="step" cols="3" class="- topic/tgroup "><colspec colname="col1" colnum="1" colwidth="10*" class="- topic/colspec "/><colspec colname="col2" colnum="2" colwidth="50*" class="- topic/colspec "/><colspec colname="col3" colnum="3" colwidth="40*" class="- topic/colspec "/><thead valign="top" class="- topic/thead "><row class="- topic/row "><entry colname="col1" align="left" valign="top" class="- topic/entry "><p class="- topic/p ">Step 
</p></entry><entry colname="col2" align="left" valign="top" class="- topic/entry "><p class="- topic/p ">Action 
</p></entry><entry colname="col3" align="left" valign="top" class="- topic/entry "><p class="- topic/p ">Remarks 
</p></entry></row></thead><tbody valign="top" class="- topic/tbody "><row class="- topic/row "><entry colname="col1" align="left" valign="top" class="- topic/entry "><p class="- topic/p ">1 
</p></entry><entry colname="col2" align="left" valign="top" class="- topic/entry "><p class="- topic/p ">Optional: 
<b class="+ topic/ph hi-d/b ">only when White functionality is required and white printhead is installed.</b> 
</p><p class="- topic/p ">Set the white hardware installed: 
</p><p class="- topic/p ">Do 
<xref href="GUID-0A54BE35-DD2E-4DD3-B683-1BE73711726B.xml" scope="local" format="dita" class="- topic/xref " type="task"><?ditaot gentext?>02-1-007 White Ink Hardware Installed</xref>. 
</p><p class="- topic/p "> Set the correct configuration (Default: No white available). 
</p></entry><entry colname="col3" align="left" valign="top" class="- topic/entry "><p class="- topic/p ">When white hardware installed is 
<b class="+ topic/ph hi-d/b ">false</b> the ui will not show White ink cartridges after reboot. 
</p><p class="- topic/p ">White ink circulation will not work. 
</p><p class="- topic/p ">White printhead will not kept healthy. 
</p></entry></row><row class="- topic/row "><entry colname="col1" align="left" valign="top" class="- topic/entry "><p class="- topic/p ">2 
</p></entry><entry colname="col2" align="left" valign="top" class="- topic/entry "><p class="- topic/p ">Restart the system via de UI to activate the configuration. 
</p></entry><entry colname="col3" align="left" valign="top" class="- topic/entry "><p class="- topic/p ">After the first or second reboot, in the right-upper corner of the ui the M3W or M5W should be visible. 
</p></entry></row></tbody></tgroup></table></section><section id="GUID-13993DD7-8B9B-4E27-B3E1-B5E350E458F9" class="- topic/section "><title class="- topic/title ">Leave SDS</title></section><section id="GUID-70F48FB9-8C55-4BDE-9321-8B8EFA7C0CDD" class="- topic/section "><title class="- topic/title ">Load Ink</title><table pgwide="1" id="GUID-BA035E84-3172-49D4-803D-07DC19E958F1" class="- topic/table "><tgroup align="left" outputclass="step" cols="3" class="- topic/tgroup "><colspec colname="col1" colnum="1" colwidth="10*" class="- topic/colspec "/><colspec colname="col2" colnum="2" colwidth="50*" class="- topic/colspec "/><colspec colname="col3" colnum="3" colwidth="40*" class="- topic/colspec "/><thead valign="top" class="- topic/thead "><row class="- topic/row "><entry colname="col1" align="left" valign="top" class="- topic/entry "><p class="- topic/p ">Step 
</p></entry><entry colname="col2" align="left" valign="top" class="- topic/entry "><p class="- topic/p ">Action 
</p></entry><entry colname="col3" align="left" valign="top" class="- topic/entry "><p class="- topic/p ">Remarks 
</p></entry></row></thead><tbody valign="top" class="- topic/tbody "><row class="- topic/row "><entry colname="col1" align="left" valign="top" class="- topic/entry "><p class="- topic/p ">1 
</p></entry><entry colname="col2" align="left" valign="top" class="- topic/entry "><p class="- topic/p ">Check the ink levels on the UI. They must be 0%. 
</p><p class="- topic/p "> If one or more levels are higher than 0%, go to SDS and reset the ink levels / mark the jars empty. SDS 02-6-004. 
</p></entry><entry colname="col3" align="left" valign="top" class="- topic/entry "><p class="- topic/p ">Both 0.7 and 1L ink bottles will be accepted as long as the license file is not installed. 
</p><p class="- topic/p ">Later on the M3 license will only accept 0.7 L bottles. 
</p></entry></row><row class="- topic/row "><entry colname="col1" align="left" valign="top" class="- topic/entry "><p class="- topic/p ">2 
</p></entry><entry colname="col2" align="left" valign="top" class="- topic/entry "><p class="- topic/p ">Load the ink bottles. 
</p><note type="important" id="GUID-64C2CF5C-4DEE-45B7-B5B7-3C0E99E57230" class="- topic/note "><p class="- topic/p ">Shake the ink cartridges ( YMCK bottles) well (10 seconds or more). 
</p><p class="- topic/p ">Shake the (W) bottle 30 seconds. 
</p></note><p class="- topic/p ">Place immediately one set of 4 (5) ink cartridges (left to right hand side: Y, C, M and K). And W (optional) 
</p><p class="- topic/p ">Wait till the led's of the ink cartridges are switched on and the bottles are detected. 
</p><p class="- topic/p ">Release the handle of the cartridges. 
</p></entry><entry colname="col3" align="left" valign="top" class="- topic/entry "><note id="GUID-789CBC72-1215-4B62-B455-BE3B55B2F968" class="- topic/note "><p class="- topic/p ">Show the key operator how to load the ink bottles. 
</p><p class="- topic/p "> The system will give a ORE message (270001) to remind you that the ink valves of the printhead should be open! 
</p></note></entry></row></tbody></tgroup></table></section><section id="GUID-3E0D34DF-59F2-4A2C-AFF5-C4703F9E2847" class="- topic/section "><title class="- topic/title ">Enter SDS</title><table pgwide="1" id="GUID-F6CEBC50-10E4-4B7C-9F84-CC64A0B31F5C" class="- topic/table "><tgroup align="left" outputclass="step" cols="3" class="- topic/tgroup "><colspec colname="col1" colnum="1" colwidth="10*" class="- topic/colspec "/><colspec colname="col2" colnum="2" colwidth="50*" class="- topic/colspec "/><colspec colname="col3" colnum="3" colwidth="40*" class="- topic/colspec "/><thead valign="top" class="- topic/thead "><row class="- topic/row "><entry colname="col1" align="left" valign="top" class="- topic/entry "><p class="- topic/p ">Step 
</p></entry><entry colname="col2" align="left" valign="top" class="- topic/entry "><p class="- topic/p ">Action 
</p></entry><entry colname="col3" align="left" valign="top" class="- topic/entry "><p class="- topic/p ">Remarks 
</p></entry></row></thead><tbody valign="top" class="- topic/tbody "><row class="- topic/row "><entry colname="col1" align="left" valign="top" class="- topic/entry "><p class="- topic/p ">1 
</p></entry><entry colname="col2" align="left" valign="top" class="- topic/entry "><p class="- topic/p ">Insert the SAM key and start SDS 
</p><p class="- topic/p ">See : 
<xref keyref="SDS01" class="- topic/xref " href="GUID-60790B61-6280-4724-A0A6-9A9E00941745.xml" format="dita" locktitle="yes" type="task"><?ditaot usertext?><?xm-replace_text How to enter SDS?>How to enter SDS</xref>. 
</p></entry><entry colname="col3" align="left" valign="top" class="- topic/entry "/></row></tbody></tgroup></table></section><section id="GUID-9AA84163-1F2D-4833-ACDA-DE92FD4455AC" class="- topic/section "><title class="- topic/title ">SDS Task [A] Load media</title><table id="TABLE_77D6483D6DAB4FD1BA8424A29FA75649" pgwide="1" class="- topic/table "><tgroup align="left" outputclass="step" cols="3" class="- topic/tgroup "><colspec colname="col1" colnum="1" colwidth="10*" class="- topic/colspec "/><colspec colname="col2" colnum="2" colwidth="50*" class="- topic/colspec "/><colspec colname="col3" colnum="3" colwidth="40*" class="- topic/colspec "/><thead valign="top" class="- topic/thead "><row class="- topic/row "><entry colname="col1" align="left" valign="top" class="- topic/entry "><p class="- topic/p ">Step 
</p></entry><entry colname="col2" align="left" valign="top" class="- topic/entry "><p class="- topic/p ">Action 
</p></entry><entry colname="col3" align="left" valign="top" class="- topic/entry "><p class="- topic/p ">Remarks 
</p></entry></row></thead><tbody valign="top" class="- topic/tbody "><row class="- topic/row "><entry colname="col1" align="left" valign="top" class="- topic/entry "><p class="- topic/p ">1 
</p></entry><entry colname="col2" align="left" valign="top" class="- topic/entry "><p class="- topic/p ">Measure the media thickness of the installation media. 
</p><p class="- topic/p "> Enter the media thickness in µm in the corresponding parameter. 
</p><p class="- topic/p ">MediaThicknessServiceTestPaper: 
<xref keyref="SDS25-1-006" class="- topic/xref " href="GUID-E1376CFC-53DD-41B7-BC10-10CBF8A7CF75.xml" format="dita" locktitle="yes" type="task"><?ditaot usertext?><?xm-replace_text 25-1-006 Media thickness of Service tests - Paper media [um] [Parameters]?>25-1-006 Media thickness of Service tests - Paper media [um] [Parameters]</xref> 
</p><p class="- topic/p ">MediaThicknessServiceTestVinyl: 
<xref keyref="SDS25-1-004" class="- topic/xref " href="GUID-826D615A-727F-419F-95A1-320B551FB319.xml" format="dita" locktitle="yes" type="task"><?ditaot usertext?><?xm-replace_text 25-1-004 Media thickness of Service tests - Vinyl media [µm] [Parameters]?>25-1-004 Media thickness of Service tests - Vinyl media [µm] [Parameters]</xref> 
</p><p class="- topic/p "> MediaThicknessServiceTestFilm: 
<xref keyref="SDS25-1-005" class="- topic/xref " href="GUID-96D4284A-979E-4C56-B741-B435D7F5B276.xml" format="dita" locktitle="yes" type="task"><?ditaot usertext?><?xm-replace_text 25-1-005 Media thickness of Service tests - Film media [um] [Parameters]?>25-1-005 Media thickness of Service tests - Film media [um] [Parameters]</xref> 
</p></entry><entry colname="col3" align="left" valign="top" class="- topic/entry "><p class="- topic/p ">For details see : 
<xref keyref="TaskA" class="- topic/xref " href="GUID-EFDCA5E9-0C61-4E2D-B738-3355445655D9.xml" format="dita" locktitle="yes" type="task"><?ditaot usertext?><?xm-replace_text Task [A] Set the media thickness for the calibration media [Tasks]?>Task [A] Set the media thickness for the calibration media [Tasks]</xref> 
</p><p class="- topic/p ">See 
<xref keyref="12adju002" class="- topic/xref " href="GUID-E9976EFB-9920-4523-8E63-376189B17D02.xml" format="dita" locktitle="yes" type="task"><?ditaot usertext?><?xm-replace_text 12 How to measure the media thickness?>12 How to measure the media thickness</xref> 
</p></entry></row><row class="- topic/row "><entry colname="col1" align="left" valign="top" class="- topic/entry "><p class="- topic/p ">2 
</p></entry><entry colname="col2" align="left" valign="top" class="- topic/entry "><p class="- topic/p ">Load the media for the media calibration on roll 1: 
</p><ul class="- topic/ul "><li class="- topic/li "><p class="- topic/p ">minimum width 50 inch (1270 mm) 
</p></li><li class="- topic/li "><p class="- topic/p ">white and smooth surface 
</p></li><li class="- topic/li "><p class="- topic/p ">the media should not be too thin 
</p></li><li class="- topic/li "><p class="- topic/p "> the media should also be usable in loose winding 
</p></li><li class="- topic/li "><p class="- topic/p ">the media should fall in one of the media categories "film", "paper", "vinyl". 
</p><p class="- topic/p ">Example: MPI 2000 (preferred) 
</p></li></ul></entry><entry colname="col3" align="left" valign="top" class="- topic/entry "><note id="GUID-ED8ABCC9-01BC-424E-B548-2D2BB643A564" class="- topic/note "><p class="- topic/p ">When you load the media, you have to enter the media width by hand. 
</p></note></entry></row><row class="- topic/row "><entry colname="col1" align="left" valign="top" class="- topic/entry "><p class="- topic/p ">3 
</p></entry><entry colname="col2" align="left" valign="top" class="- topic/entry "/><entry colname="col3" align="left" valign="top" class="- topic/entry "/></row></tbody></tgroup></table></section><section id="GUID-86EF0C67-3037-4270-9AA4-1BF1A61C2352" class="- topic/section "><title class="- topic/title ">SDS Task [B] Printhead and Engine calibrations</title><table id="TABLE_18C2338C364749D2A7DD995B69033234" pgwide="1" class="- topic/table "><tgroup align="left" outputclass="step" cols="4" class="- topic/tgroup "><colspec colname="col1" colnum="1" colwidth="10*" class="- topic/colspec "/><colspec colname="col2" colnum="2" colwidth="50*" class="- topic/colspec "/><colspec colname="col3" colnum="3" colwidth="3.59*" class="- topic/colspec "/><colspec colname="col4" colnum="4" colwidth="40*" class="- topic/colspec "/><thead valign="top" class="- topic/thead "><row class="- topic/row "><entry colname="col1" align="left" valign="top" class="- topic/entry "><p class="- topic/p ">Step 
</p></entry><entry colname="col2" namest="col2" nameend="col3" align="left" valign="top" class="- topic/entry "><p class="- topic/p ">Action 
</p></entry><entry colname="col4" align="left" valign="top" class="- topic/entry "><p class="- topic/p ">Remarks 
</p></entry></row></thead><tbody valign="top" class="- topic/tbody "><row class="- topic/row "><entry colname="col1" align="left" valign="top" class="- topic/entry "><p class="- topic/p ">1 
</p></entry><entry colname="col2" namest="col2" nameend="col3" align="left" valign="top" class="- topic/entry "><p class="- topic/p "> Set the output configuration to 
<b class="+ topic/ph hi-d/b ">Wind the output = NO</b>. 
</p></entry><entry colname="col4" align="left" valign="top" class="- topic/entry "/></row><row class="- topic/row "><entry colname="col1" align="left" valign="top" class="- topic/entry "><p class="- topic/p ">2 
</p></entry><entry colname="col2" namest="col2" nameend="col3" align="left" valign="top" class="- topic/entry "><p class="- topic/p ">Wait until the printer is ready. 
</p><p class="- topic/p ">This may take a while (~15 minutes) since the initial ink filling procedure is now running. 
</p></entry><entry colname="col4" align="left" valign="top" class="- topic/entry "><p class="- topic/p ">For details see : 
<xref keyref="TaskB" class="- topic/xref " href="GUID-D4FABA75-EA44-4653-B5D3-29C0DF48A81C.xml" format="dita" locktitle="yes" type="task"><?ditaot usertext?><?xm-replace_text Task [B] Printhead and Engine Calibrations [Tasks]?>Task [B] Printhead and Engine Calibrations [Tasks]</xref> 
</p></entry></row><row class="- topic/row "><entry colname="col1" align="left" valign="top" class="- topic/entry "><p class="- topic/p ">3 
</p></entry><entry colname="col2" namest="col2" nameend="col3" align="left" valign="top" class="- topic/entry "><p class="- topic/p ">Execute the steps in the given order of SDS task [B] 
</p></entry><entry colname="col4" align="left" valign="top" class="- topic/entry "/></row></tbody></tgroup></table></section><section id="GUID-E3C10126-25DF-4B8F-B20E-ABD1A6308574" class="- topic/section "><title class="- topic/title ">Print the Demo Print</title><table pgwide="1" id="GUID-BA5EAA29-343F-4AEC-A2FF-4FD1D33A0ABE" class="- topic/table "><tgroup align="left" outputclass="step" cols="4" class="- topic/tgroup "><colspec colname="col1" colnum="1" colwidth="10*" class="- topic/colspec "/><colspec colname="col2" colnum="2" colwidth="50*" class="- topic/colspec "/><colspec colname="col3" colnum="3" colwidth="3.59*" class="- topic/colspec "/><colspec colname="col4" colnum="4" colwidth="40*" class="- topic/colspec "/><thead valign="top" class="- topic/thead "><row class="- topic/row "><entry colname="col1" align="left" valign="top" class="- topic/entry "><p class="- topic/p ">Step 
</p></entry><entry colname="col2" namest="col2" nameend="col3" align="left" valign="top" class="- topic/entry "><p class="- topic/p ">Action 
</p></entry><entry colname="col4" align="left" valign="top" class="- topic/entry "><p class="- topic/p ">Remarks 
</p></entry></row></thead><tbody valign="top" class="- topic/tbody "><row class="- topic/row "><entry colname="col1" align="left" valign="top" class="- topic/entry "><p class="- topic/p ">1 
</p></entry><entry colname="col2" namest="col2" nameend="col3" align="left" valign="top" class="- topic/entry "><p class="- topic/p "> Print the Demo Print from the operator panel. 
</p></entry><entry colname="col4" align="left" valign="top" class="- topic/entry "><p class="- topic/p "> Do not cut the media after it has been printed. This is saves media for the next SDS test. 
</p><note id="GUID-B268665D-C7C8-4F88-8B88-755879D24B22" class="- topic/note "><p class="- topic/p ">The Demo Print output is depending on the hardware configuration. (Gloss, Matt, Flex Finnish+and White). 
</p></note></entry></row></tbody></tgroup></table></section><section id="GUID-1C21B6A3-6153-4AEB-B3DE-3D1774B0FC1B" class="- topic/section "><title class="- topic/title ">Install licenses</title><table pgwide="1" id="GUID-79CC64A9-592D-4947-BEDE-BFC787F944C7" class="- topic/table "><tgroup align="left" outputclass="step" cols="3" class="- topic/tgroup "><colspec colname="col1" colnum="1" colwidth="10*" class="- topic/colspec "/><colspec colname="col2" colnum="2" colwidth="50*" class="- topic/colspec "/><colspec colname="col3" colnum="3" colwidth="40*" class="- topic/colspec "/><thead valign="top" class="- topic/thead "><row class="- topic/row "><entry colname="col1" align="left" valign="top" class="- topic/entry "><p class="- topic/p ">Step 
</p></entry><entry colname="col2" align="left" valign="top" class="- topic/entry "><p class="- topic/p ">Action 
</p></entry><entry colname="col3" align="left" valign="top" class="- topic/entry "><p class="- topic/p ">Remarks 
</p></entry></row></thead><tbody valign="top" class="- topic/tbody "><row class="- topic/row "><entry colname="col1" align="left" valign="top" class="- topic/entry "><p class="- topic/p ">1 
</p></entry><entry colname="col2" align="left" valign="top" class="- topic/entry "><p class="- topic/p ">Install the (base) license(s) you received via ORS. 
</p><p class="- topic/p ">See: 
<xref keyref="GEN_INST_LICENSE_ORS_001" class="- topic/xref " href="GUID-4D9B803A-BA12-4035-80B2-CFBB77288B40.xml" format="dita" locktitle="yes" type="task"><?ditaot usertext?><?xm-replace_text Install a license via ORS?>Install a license via ORS</xref> 
</p><p class="- topic/p ">The alternative is to install the (base) license(s) you received via email. 
</p><p class="- topic/p ">see: 
<xref keyref="GENINSTLICENCE002" class="- topic/xref " href="GUID-A5731826-4ADE-4A39-807A-9F6B14629783.xml" format="dita" locktitle="yes" type="task"><?ditaot usertext?><?xm-replace_text Install a license received via e-mail?>Install a license received via e-mail</xref> 
</p></entry><entry colname="col3" align="left" valign="top" class="- topic/entry "><p class="- topic/p ">Verify if the expected licenses are also visible on the UI, otherwise printing from RIP is not possible. 
</p></entry></row></tbody></tgroup></table></section><section id="GUID-275FF3F0-45F6-4E49-8EFA-940132676599" class="- topic/section "><title class="- topic/title ">Finalize the printer</title><table pgwide="1" id="GUID-2F8CFD75-9D87-4E22-86BE-96AF8A0FD2A6" class="- topic/table "><tgroup align="left" outputclass="step" cols="3" class="- topic/tgroup "><colspec colname="col1" colnum="1" colwidth="10*" class="- topic/colspec "/><colspec colname="col2" colnum="2" colwidth="50*" class="- topic/colspec "/><colspec colname="col3" colnum="3" colwidth="40*" class="- topic/colspec "/><thead valign="top" class="- topic/thead "><row class="- topic/row "><entry colname="col1" align="left" valign="top" class="- topic/entry "><p class="- topic/p ">Step 
</p></entry><entry colname="col2" align="left" valign="top" class="- topic/entry "><p class="- topic/p ">Action 
</p></entry><entry colname="col3" align="left" valign="top" class="- topic/entry "><p class="- topic/p ">Remarks 
</p></entry></row></thead><tbody valign="top" class="- topic/tbody "><row class="- topic/row "><entry colname="col1" align="left" valign="top" class="- topic/entry "><p class="- topic/p ">1 
</p></entry><entry colname="col2" align="left" valign="top" class="- topic/entry "><p class="- topic/p ">Remove the foil of the top cover. 
</p></entry><entry colname="col3" align="left" valign="top" class="- topic/entry "/></row><row class="- topic/row "><entry colname="col1" align="left" valign="top" class="- topic/entry "><p class="- topic/p ">2 
</p></entry><entry colname="col2" align="left" valign="top" class="- topic/entry "><p class="- topic/p ">Install the lower cover. 
</p><p class="- topic/p ">See 
<xref keyref="GENINSTCOVERS002" class="- topic/xref " href="GUID-96F9FF64-25D2-4811-93E7-BF1426ED831E.xml" format="dita" locktitle="yes" type="task"><?ditaot usertext?><?xm-replace_text Install the media output lower cover?>Install the media output lower cover</xref> 
</p></entry><entry colname="col3" align="left" valign="top" class="- topic/entry "/></row><row class="- topic/row "><entry colname="col1" align="left" valign="top" class="- topic/entry "><p class="- topic/p ">3 
</p></entry><entry colname="col2" align="left" valign="top" class="- topic/entry "><p class="- topic/p ">Place the transport locking material, printhead blisters and media in area below the media drawer. 
</p></entry><entry colname="col3" align="left" valign="top" class="- topic/entry "/></row><row class="- topic/row "><entry colname="col1" align="left" valign="top" class="- topic/entry "><p class="- topic/p ">4 
</p></entry><entry colname="col2" align="left" valign="top" class="- topic/entry "><p class="- topic/p ">Mount all covers on the printer. 
</p></entry><entry colname="col3" align="left" valign="top" class="- topic/entry "/></row><row class="- topic/row "><entry colname="col1" align="left" valign="top" class="- topic/entry "><p class="- topic/p ">5 
</p></entry><entry colname="col2" align="left" valign="top" class="- topic/entry "><p class="- topic/p ">Place the grip lock on the cover beside the media drawer. 
</p></entry><entry colname="col3" align="left" valign="top" class="- topic/entry "><fig id="GUID-199A782F-D034-4A2E-82DD-F6199A8C8F5D" class="- topic/fig "><title class="- topic/title "/><image href="GUID-2F662DF5-25A1-427E-A6D8-A691A6A116C3-low.png" keyref="" placement="inline" class="- topic/image " otherprops="GUID-2F662DF5-25A1-427E-A6D8-A691A6A116C3-low.png"/></fig></entry></row></tbody></tgroup></table></section><section id="GUID-5F62FF3C-B2C6-436C-90C7-0D1D6AEBCB15" class="- topic/section "><title class="- topic/title ">RIP</title><table id="TABLE_2D33F156AE1749229350233964232A5C" pgwide="1" class="- topic/table "><tgroup align="left" outputclass="step" cols="3" class="- topic/tgroup "><colspec colname="col1" colnum="1" colwidth="10*" class="- topic/colspec "/><colspec colname="col2" colnum="2" colwidth="50*" class="- topic/colspec "/><colspec colname="col3" colnum="3" colwidth="40*" class="- topic/colspec "/><thead valign="top" class="- topic/thead "><row class="- topic/row "><entry colname="col1" align="left" valign="top" class="- topic/entry "><p class="- topic/p ">Step 
</p></entry><entry colname="col2" align="left" valign="top" class="- topic/entry "><p class="- topic/p ">Action 
</p></entry><entry colname="col3" align="left" valign="top" class="- topic/entry "><p class="- topic/p ">Remarks 
</p></entry></row></thead><tbody valign="top" class="- topic/tbody "><row class="- topic/row "><entry colname="col1" align="left" valign="top" class="- topic/entry "><p class="- topic/p ">1 
</p></entry><entry colname="col2" align="left" valign="top" class="- topic/entry "><p class="- topic/p ">Connect to the RIP. 
</p><p class="- topic/p "><b class="+ topic/ph hi-d/b ">Onyx</b>: 
</p><ul id="UL_80A00B677F164B6B896AC3673E4D1D4C" class="- topic/ul "><li id="LI_133613DF68D24945B61EC5D84D969BEB" class="- topic/li "><p class="- topic/p ">Do 
<xref keyref="Onyx_install_001" class="- topic/xref " href="GUID-A0CF4E06-375D-4F8F-9407-FAC17310F5FF.xml" format="dita" locktitle="yes" type="task"><?ditaot usertext?><?xm-replace_text How to install the Colorado printer driver in ONYX?>How to install the Colorado printer driver in ONYX</xref> 
</p></li><li id="LI_AE931237996045549C991C1849E14D72" class="- topic/li "><p class="- topic/p "><xref keyref="Upgrade_Onyx" class="- topic/xref " href="GUID-47163028-5130-46C2-9D99-8F0F03EB2B6E.xml" format="dita" locktitle="yes" type="task"><?ditaot usertext?><?xm-replace_text How to upgrade the ONYX printer driver?>How to upgrade the ONYX printer driver</xref> 
</p></li></ul></entry><entry colname="col3" align="left" valign="top" class="- topic/entry "/></row><row class="- topic/row "><entry colname="col1" align="left" valign="top" class="- topic/entry "><p class="- topic/p ">2 
</p></entry><entry colname="col2" align="left" valign="top" class="- topic/entry "><p class="- topic/p ">Print from RIP. 
</p><p class="- topic/p "><b class="+ topic/ph hi-d/b ">Onyx</b>: 
</p><p class="- topic/p ">Do 
<xref keyref="Onyx_install_004" class="- topic/xref " href="GUID-2FB6105E-9D58-4917-9A1A-C36A83AE8A79.xml" format="dita" locktitle="yes" type="task"><?ditaot usertext?><?xm-replace_text Print the ONYX test print?>Print the ONYX test print</xref> 
</p></entry><entry colname="col3" align="left" valign="top" class="- topic/entry "/></row></tbody></tgroup></table></section><section id="GUID-736B225C-5CEB-475A-AC18-45F135E6E0AA" class="- topic/section "><title class="- topic/title ">Settings editor and Operation guide </title><table id="GUID-72C04720-9B90-473B-9589-7004B09C1C86" pgwide="1" class="- topic/table "><tgroup align="left" outputclass="step" cols="3" class="- topic/tgroup "><colspec colname="col1" colnum="1" colwidth="10*" class="- topic/colspec "/><colspec colname="col2" colnum="2" colwidth="50*" class="- topic/colspec "/><colspec colname="col3" colnum="3" colwidth="40*" class="- topic/colspec "/><thead valign="top" class="- topic/thead "><row class="- topic/row "><entry colname="col1" align="left" valign="top" class="- topic/entry "><p class="- topic/p ">Step 
</p></entry><entry colname="col2" align="left" valign="top" class="- topic/entry "><p class="- topic/p ">Action 
</p></entry><entry colname="col3" align="left" valign="top" class="- topic/entry "><p class="- topic/p ">Remarks 
</p></entry></row></thead><tbody valign="top" class="- topic/tbody "><row class="- topic/row "><entry colname="col1" align="left" valign="top" class="- topic/entry "><p class="- topic/p ">1 
</p></entry><entry colname="col2" align="left" valign="top" class="- topic/entry "><p class="- topic/p ">Ask the customer to create a shortcut to the Settings editor on a customers PC. 
</p><p class="- topic/p "> Access the Settings editor via any web browser, by typing in the printer's: 
</p><ul class="- topic/ul "><li class="- topic/li "><p class="- topic/p ">IP address 
</p><p class="- topic/p ">or 
</p></li><li class="- topic/li "><p class="- topic/p "> Hostname 
</p></li></ul><p class="- topic/p ">Use the link to create a shortcut on the desktop. 
</p></entry><entry colname="col3" align="left" valign="top" class="- topic/entry "/></row><row class="- topic/row "><entry colname="col1" align="left" valign="top" class="- topic/entry "><p class="- topic/p ">2 
</p></entry><entry colname="col2" align="left" valign="top" class="- topic/entry "><p class="- topic/p "> Install the Operation guide. 
</p></entry><entry colname="col3" align="left" valign="top" class="- topic/entry "/></row></tbody></tgroup></table></section><section id="GUID-40872B37-9A4C-4795-A6CE-F747365DB86F" class="- topic/section "><title class="- topic/title ">Remote Service (ORS)</title><table id="TABLE_8AFD9221C388443DAD4E8E3BD68B77D4" pgwide="1" class="- topic/table "><tgroup align="left" outputclass="step" cols="3" class="- topic/tgroup "><colspec colname="col1" colnum="1" colwidth="10*" class="- topic/colspec "/><colspec colname="col2" colnum="2" colwidth="50*" class="- topic/colspec "/><colspec colname="col3" colnum="3" colwidth="40*" class="- topic/colspec "/><thead valign="top" class="- topic/thead "><row class="- topic/row "><entry colname="col1" align="left" valign="top" class="- topic/entry "><p class="- topic/p ">Step 
</p></entry><entry colname="col2" align="left" valign="top" class="- topic/entry "><p class="- topic/p ">Action 
</p></entry><entry colname="col3" align="left" valign="top" class="- topic/entry "><p class="- topic/p ">Remarks 
</p></entry></row></thead><tbody valign="top" class="- topic/tbody "><row class="- topic/row "><entry colname="col1" align="left" valign="top" class="- topic/entry "><p class="- topic/p ">1 
</p></entry><entry colname="col2" align="left" valign="top" class="- topic/entry "><p class="- topic/p ">Set-up Remote Service (If not done yet). 
</p><p class="- topic/p ">See 
<xref keyref="ORSSETUP001" class="- topic/xref " href="GUID-07BC7664-5AAE-4C27-A331-C2F6D4AB2349.xml" format="dita" locktitle="yes" type="task"><?ditaot usertext?><?xm-replace_text How to set up On Remote Service (ORS)?>How to set up On Remote Service (ORS)</xref> 
</p></entry><entry colname="col3" align="left" valign="top" class="- topic/entry "/></row></tbody></tgroup></table></section><section id="GUID-543DF028-1ABD-4ABF-98DD-B144C8DF5882" class="- topic/section "><title class="- topic/title ">HTML TSM</title><table id="TABLE_920DBE9262C0485B8A080650DE541812" pgwide="1" class="- topic/table "><tgroup align="left" outputclass="step" cols="3" class="- topic/tgroup "><colspec colname="col1" colnum="1" colwidth="10*" class="- topic/colspec "/><colspec colname="col2" colnum="2" colwidth="50*" class="- topic/colspec "/><colspec colname="col3" colnum="3" colwidth="40*" class="- topic/colspec "/><thead valign="top" class="- topic/thead "><row class="- topic/row "><entry colname="col1" align="left" valign="top" class="- topic/entry "><p class="- topic/p ">Step 
</p></entry><entry colname="col2" align="left" valign="top" class="- topic/entry "><p class="- topic/p ">Action 
</p></entry><entry colname="col3" align="left" valign="top" class="- topic/entry "><p class="- topic/p ">Remarks 
</p></entry></row></thead><tbody valign="top" class="- topic/tbody "><row class="- topic/row "><entry colname="col1" align="left" valign="top" class="- topic/entry "><p class="- topic/p ">1 
</p></entry><entry colname="col2" align="left" valign="top" class="- topic/entry "><p class="- topic/p ">Set-up the TSM with a USB key or ORS. 
</p><p class="- topic/p ">See 
<xref keyref="HTMLRobin004" class="- topic/xref " href="GUID-9F86EFE8-588D-4B84-A174-4CA4038D6670.xml" format="dita" locktitle="yes" type="task"><?ditaot usertext?><?xm-replace_text Install the HTML TSM from a USB key?>Install the HTML TSM from a USB key</xref> 
</p><p class="- topic/p ">See 
<xref keyref="HTMLORS001" class="- topic/xref " href="GUID-2627AC38-117B-44C1-AD22-59CB29A2B34F.xml" format="dita" locktitle="yes" type="task"><?ditaot usertext?><?xm-replace_text Install the embedded HTML TSM?>Install the embedded HTML TSM</xref> 
</p></entry><entry colname="col3" align="left" valign="top" class="- topic/entry "><p class="- topic/p ">Optional: Standard HTML TSM is already installed. 
</p></entry></row></tbody></tgroup></table></section><section id="GUID-9AB526BF-1A30-43F6-A3F6-D19930A88464" class="- topic/section "><title class="- topic/title ">Customer instruction</title><table id="M148553-TB102" pgwide="1" class="- topic/table "><tgroup align="left" outputclass="step" cols="3" class="- topic/tgroup "><colspec colname="col1" colnum="1" colwidth="10*" class="- topic/colspec "/><colspec colname="col2" colnum="2" colwidth="50*" class="- topic/colspec "/><colspec colname="col3" colnum="3" colwidth="40*" class="- topic/colspec "/><thead valign="top" class="- topic/thead "><row class="- topic/row "><entry colname="col1" align="left" valign="top" class="- topic/entry "><p class="- topic/p ">Step 
</p></entry><entry colname="col2" align="left" valign="top" class="- topic/entry "><p class="- topic/p ">Action 
</p></entry><entry colname="col3" align="left" valign="top" class="- topic/entry "><p class="- topic/p ">Remarks 
</p></entry></row></thead><tbody valign="top" class="- topic/tbody "><row class="- topic/row "><entry colname="col1" align="left" valign="top" class="- topic/entry "><p class="- topic/p ">1 
</p></entry><entry colname="col2" align="left" valign="top" class="- topic/entry "><p class="- topic/p ">Carry out the Quick Start instruction. 
</p><p class="- topic/p ">See 
<xref keyref="1.0.0.Quickstart" class="- topic/xref " href="GUID-A55DBC84-C502-45E0-B779-DC9D1AC3901F.xml" format="dita" locktitle="yes" type="task"><?ditaot usertext?><?xm-replace_text Quick Start instruction?>Quick Start instruction</xref>. 
</p></entry><entry colname="col3" align="left" valign="top" class="- topic/entry "><note id="GUID-FFA04B15-0B4D-4033-B676-713245B7A026" class="- topic/note "><p class="- topic/p ">For Germany only: Hand over the hard copy of the operation guide (with the safety information). 
</p></note></entry></row></tbody></tgroup></table></section><section id="GUID-3E1A93FC-943A-4446-8284-4D2FBF822869" class="- topic/section "><title class="- topic/title ">Finalize</title><table id="TABLE_BACC0E62E5FD451DA24A70BB6F845040" pgwide="1" class="- topic/table "><tgroup align="left" outputclass="step" cols="3" class="- topic/tgroup "><colspec colname="col1" colnum="1" colwidth="10*" class="- topic/colspec "/><colspec colname="col2" colnum="2" colwidth="50*" class="- topic/colspec "/><colspec colname="col3" colnum="3" colwidth="40*" class="- topic/colspec "/><thead valign="top" class="- topic/thead "><row class="- topic/row "><entry colname="col1" align="left" valign="top" class="- topic/entry "><p class="- topic/p ">Step 
</p></entry><entry colname="col2" align="left" valign="top" class="- topic/entry "><p class="- topic/p ">Action 
</p></entry><entry colname="col3" align="left" valign="top" class="- topic/entry "><p class="- topic/p ">Remarks 
</p></entry></row></thead><tbody valign="top" class="- topic/tbody "><row class="- topic/row "><entry colname="col1" align="left" valign="top" class="- topic/entry "><p class="- topic/p ">1 
</p></entry><entry colname="col2" align="left" valign="top" class="- topic/entry "><p class="- topic/p "> Create and Save the installation visit in ADAM. 
</p><ul class="- topic/ul "><li class="- topic/li "><p class="- topic/p ">Please indicate the time estimate you have spent on the installation. 
</p></li><li class="- topic/li "><p class="- topic/p "> Please indicate all the issues found as separate items in the collect phase. 
</p></li></ul></entry><entry colname="col3" align="left" valign="top" class="- topic/entry "><p class="- topic/p "> The installation visit in ADAM is replacing the paper feedback form. 
</p></entry></row><row class="- topic/row "><entry colname="col1" align="left" valign="top" class="- topic/entry "><p class="- topic/p ">2 
</p></entry><entry colname="col2" align="left" valign="top" class="- topic/entry "><p class="- topic/p ">Do not forget to check/enter the modifications in SDS. 
</p><p class="- topic/p "> (both from the yellow modification label and if applicable the firmware update) 
</p></entry><entry colname="col3" align="left" valign="top" class="- topic/entry "><p class="- topic/p ">e.g. Modification 1 for Install Ink Mist suction kit 
</p></entry></row><row class="- topic/row "><entry colname="col1" align="left" valign="top" class="- topic/entry "><p class="- topic/p ">3 
</p></entry><entry colname="col2" align="left" valign="top" class="- topic/entry "><p class="- topic/p ">Store the transport packing material, blisters, foam blocks and the media of calibration at the customers place. 
</p></entry><entry colname="col3" align="left" valign="top" class="- topic/entry "/></row></tbody></tgroup></table></section></taskbody><related-links class="- topic/related-links "><linkpool class="- topic/linkpool " mapkeyref="GUID-8A41CFEA-5928-4042-A2CB-507A5D034160"><link class="- topic/link " mapclass="- map/topicref " format="dita" type="concept" href="generated-topic-GUID-7D3F358C-1AB9-4A5D-9B0E-C75D689F152E.xml" role="parent"><?ditaot usertext?><linktext class="- topic/linktext "><?ditaot usertext?>Installation</linktext></link></linkpool></related-links>
</task>