<?xml version="1.0" encoding="UTF-8"?><?ish ishref="GUID-6C2B532F-74A2-4840-B033-896FAC40D873" version="2" lang="en-US"?><task xmlns:ditaarch="http://dita.oasis-open.org/architecture/2005/" id="GUID-6C2B532F-74A2-4840-B033-896FAC40D873" xml:lang="en-US" ditaarch:DITAArchVersion="1.3" domains="(topic task)                            (topic hi-d)                            (topic ui-d)                            (topic sw-d)                            (topic indexing-d)                            (topic ut-d)                            a(base ishcondition)                            a(base varid)                            a(base varref)                            a(base cid)                            a(base partslist)                            (topic oce-d)                            (topic sdlVariables-c)                            (topic oceCommonElements-c)                            (topic oceMetaDecl-c)                            (topic oceTopic-c)                            (topic oceTopic-c task oceTask-c)                            (topic oceTopic-c hi-d oceHighlight-c)                            (topic oceTopic-c ui-d oceUi-c)                            (topic oceTopic-c sw-d oceSoftware-c)   " class="- topic/topic task/task "><title class="- topic/title ">12 Load media from the jumbo roll</title><abstract class="- topic/abstract " id="GUID-BDFD8435-6F00-4FEB-B145-7157CB199BBA"><p class="- topic/p "><indexterm class="- topic/indexterm ">Jumbo roll<indexterm class="- topic/indexterm ">Feed media</indexterm></indexterm><indexterm class="- topic/indexterm ">Jumbo roll unwinder<indexterm class="- topic/indexterm ">Load media</indexterm></indexterm> 
</p><p class="- topic/p ">You can find a description on how to use the jumbo roll in the separate user manual of the Fotoba jumbo roll. It describes amongst others: 
</p><ul class="- topic/ul "><li class="- topic/li "><p class="- topic/p ">how to load the media, 
</p></li><li class="- topic/li "><p class="- topic/p ">how to align the media with the printer, 
</p></li><li class="- topic/li "><p class="- topic/p ">how to spool media to make a blouse. 
</p></li></ul><p class="- topic/p ">In this document you will find information on how to load the media from the jumbo roll into the system. 
</p><p class="- topic/p ">This procedure is also explained in a separate instruction video, click 
<xref class="- topic/xref " format="html" href="https://vimeopro.com/oceitcdoctrans/oce-colorado-1650-maintenance/video/448450365" scope="external"><?ditaot usertext?>here</xref> to visit. 
</p></abstract><prolog class="- topic/prolog "><metadata class="- topic/metadata "><category class="- topic/category ">User task</category></metadata></prolog><taskbody class="- topic/body task/taskbody "><prereq id="GUID-52528625-229F-4925-B967-5F8D36B8934B" class="- topic/section task/prereq "><ul class="- topic/ul "><li class="- topic/li "><p class="- topic/p ">Check the media up-front (small roll). 
</p><p class="- topic/p ">Calibration can be performed on the media loaded on the jumbo roll. 
</p></li><li class="- topic/li "><p class="- topic/p "> Load the media roll centered onto the core on the jumbo roll. 
</p></li><li class="- topic/li "><p class="- topic/p ">On the control panel of the jumbo roll select <uicontrol class="+ topic/ph ui-d/uicontrol ">Manual transport</uicontrol>. 
</p></li></ul><note id="GUID-D68E7707-000B-4341-BDA7-2177DCF17DA4" class="- topic/note "><ul class="- topic/ul "><li class="- topic/li "><p class="- topic/p ">Load the media for outside printing is preferred. 
</p></li><li class="- topic/li "><p class="- topic/p "> Print quality is guaranteed after 1 meter (39.4 inch). 
</p><p class="- topic/p ">When the media is taped to the take-up roll. 
</p></li></ul></note><note type="important" id="GUID-1571F228-F89A-4721-ACC4-7C8003350E14" class="- topic/note "><p class="- topic/p ">Do not use the manual transport of media of the jumbo roll when the media is loaded on the printer or when the printer is in an error state. 
</p></note></prereq><steps id="GUID-B720E30E-4932-4157-B92E-6EA38B0C560F" class="- topic/ol task/steps "><step class="- topic/li task/step "><cmd class="- topic/ph task/cmd "> Place a marker on the frame of the media input unit to identify the width of the media (for example a piece of tape). 
</cmd><info class="- topic/itemgroup task/info "><fig id="GUID-7AD254F8-8223-446C-A320-C33B8B5A646B" class="- topic/fig "><image href="GUID-17F25E4B-95D9-4232-B517-31BAE2F9B78F-low.png" placement="inline" class="- topic/image " otherprops="GUID-17F25E4B-95D9-4232-B517-31BAE2F9B78F-low.png"/></fig><note id="GUID-46F7D258-F300-4F24-8BFB-BD841AEDFCB7" class="- topic/note "><fig id="GUID-AD8296A5-2AAE-46E2-8C6D-894A70942BAF" class="- topic/fig "><image href="GUID-E830C3B0-1B2A-4E4B-8CC4-EAF9A999C051-low.png" placement="inline" class="- topic/image " otherprops="GUID-E830C3B0-1B2A-4E4B-8CC4-EAF9A999C051-low.png"/></fig><p class="- topic/p ">The notch in the illustration above indicates the center of the guiding plate of the media input unit. Place the marker at a distance "media width divided by 2" from the center notch. 
</p></note></info></step><step class="- topic/li task/step "><cmd class="- topic/ph task/cmd "> Spool 21 cm (8.3 inch) of the media beyond the guiding plate (just before the last roller) of the Jumbo roll. 
</cmd></step><step class="- topic/li task/step "><cmd class="- topic/ph task/cmd "> Pull the media tight towards the roll and add a mark (line) at a distance of 21 cm (8.3 inch) from the leading edge. Do this on both sides of the media, left and right. You can use the guiding plate of the jumbo roll for reference. 
</cmd><info class="- topic/itemgroup task/info "><fig id="GUID-980C82AC-ADC5-48B9-B7C7-7D545EC3BFC6" class="- topic/fig "><image href="GUID-3089EB5F-975F-469D-8C77-BB02D7A8924E-low.png" placement="inline" class="- topic/image " otherprops="GUID-3089EB5F-975F-469D-8C77-BB02D7A8924E-low.png"/></fig><fig id="GUID-4118099D-E230-4EB9-B240-7BB20B72150C" class="- topic/fig "><image href="GUID-D94E3385-B155-4ED4-B496-802D3B482EEC-low.png" placement="inline" class="- topic/image " otherprops="GUID-D94E3385-B155-4ED4-B496-802D3B482EEC-low.png"/></fig><note id="GUID-1D3CB3C1-4743-4216-AA21-0DC9021AB0BA" class="- topic/note "><p class="- topic/p ">When you load a media with a leading edge that is not completely straight, measure like shown in the illustration below. 
</p><p class="- topic/p ">Make sure that the difference between left and right edge of the media is not be too much to prevent that the printer prints directly on the platen. 
</p><fig id="GUID-C12CC2C5-1DC6-4E2F-B017-FA50925B5FCA" class="- topic/fig "><image href="GUID-1E350CCA-3A61-49A9-87A2-00893979AC7D-low.jpg" placement="inline" class="- topic/image " otherprops="GUID-1E350CCA-3A61-49A9-87A2-00893979AC7D-low.jpg"/></fig></note></info></step><step class="- topic/li task/step "><cmd class="- topic/ph task/cmd ">Spool the media further. Stop just before the media touches the floor. 
</cmd><info class="- topic/itemgroup task/info "><fig id="GUID-D7EA92EF-1465-4153-A13E-24D59A2D3848" class="- topic/fig "><image href="GUID-1B3B773C-AC5B-4E68-8156-F029A867C1A0-low.png" placement="inline" class="- topic/image " otherprops="GUID-1B3B773C-AC5B-4E68-8156-F029A867C1A0-low.png"/></fig></info></step><step class="- topic/li task/step "><cmd class="- topic/ph task/cmd ">Before you feed the media into the printer, align the media with the marker on the printer (the tape you applied in step 1). 
</cmd><info class="- topic/itemgroup task/info "><fig id="GUID-60151320-E4B2-4388-98A0-6155F217A1D0" class="- topic/fig "><image href="GUID-17F25E4B-95D9-4232-B517-31BAE2F9B78F-low.png" placement="inline" class="- topic/image " otherprops="GUID-17F25E4B-95D9-4232-B517-31BAE2F9B78F-low.png"/></fig></info></step><step class="- topic/li task/step "><note id="GUID-5B04BD3C-D4DC-466E-83D9-615E7A12A788" class="- topic/note "><p class="- topic/p ">It is highly recommended to perform the next two steps with two persons. 
</p></note><cmd class="- topic/ph task/cmd ">Align the 2 markers (lines) on the left and right side of the media with the input unit, see illustration. Distance to red dotted line is 3 cm (1.18 inch). 
</cmd><info class="- topic/itemgroup task/info "><fig id="GUID-01E678CA-586D-4216-8B9B-2A382F55BAA2" class="- topic/fig "><image href="GUID-78019645-DFEC-4677-BF42-AB360FCFF1DB-low.png" placement="inline" class="- topic/image " otherprops="GUID-78019645-DFEC-4677-BF42-AB360FCFF1DB-low.png"/></fig><fig id="GUID-9DBCF9EE-7AD4-4797-AD2B-E468FA892A9F" class="- topic/fig "><image href="GUID-FE3C1353-A9F7-4098-80BD-C4BA2DFA621B-low.png" placement="inline" class="- topic/image " otherprops="GUID-FE3C1353-A9F7-4098-80BD-C4BA2DFA621B-low.png"/></fig></info></step><step class="- topic/li task/step "><cmd class="- topic/ph task/cmd ">Feed the media into the media input unit. The input unit pinch will start to rotate for 2 seconds and grab the media. Check the media position at the reference marker (lines) position. The allowed tolerance is <ph class="- topic/ph " outputclass="mathsymbols">± </ph>5 mm (0.19 inch) at the left and <ph class="- topic/ph " outputclass="mathsymbols">± </ph>5 mm (0.19 inch) at the right side. 
</cmd><info class="- topic/itemgroup task/info "><fig id="GUID-56251C5E-8763-4F7D-ABF5-D3A1DA36C68E" class="- topic/fig "><image href="GUID-5DBFD03D-17BF-4CB6-8510-7FFBF1E5BDD2-low.png" placement="inline" class="- topic/image " otherprops="GUID-5DBFD03D-17BF-4CB6-8510-7FFBF1E5BDD2-low.png"/></fig><p class="- topic/p ">If the position is not within the tolerance is <ph class="- topic/ph " outputclass="mathsymbols">± </ph>5 mm (0.19 inch), pull the media back (2 persons preferred) and feed again until the position is within the tolerance. 
</p></info></step><step class="- topic/li task/step "><cmd class="- topic/ph task/cmd "> Push the jumbo roll unwinder towards the printer on both sides and lock the unit. 
</cmd></step><step class="- topic/li task/step "><cmd class="- topic/ph task/cmd ">Lower the buffer unit and spool media. See illustration below. 
</cmd><info class="- topic/itemgroup task/info "><fig id="GUID-96FC30B4-8A56-4A2F-8F92-45A834E1EDCB" class="- topic/fig "><image href="GUID-7C249026-8800-41A2-AE89-AD85BB936511-low.png" placement="inline" class="- topic/image " otherprops="GUID-7C249026-8800-41A2-AE89-AD85BB936511-low.png"/></fig><p class="- topic/p ">After this, go to the control panel of the jumbo roll and select <uicontrol class="+ topic/ph ui-d/uicontrol ">Automatic transport</uicontrol> and choose the required rotating direction. 
</p></info></step></steps><postreq id="GUID-D6F9FEC4-740B-42A5-9FD1-CD9FF2524B86" class="- topic/section task/postreq "><p class="- topic/p ">On the control panel of the printer select the <uicontrol class="+ topic/ph ui-d/uicontrol ">External</uicontrol> roll for your print job from the jumbo roll. 
</p></postreq></taskbody><related-links class="- topic/related-links "><linkpool class="- topic/linkpool " mapkeyref="GUID-8A41CFEA-5928-4042-A2CB-507A5D034160"><link class="- topic/link " mapclass="- map/topicref " format="dita" type="concept" href="generated-topic-GUID-E054F15A-BCD6-47D9-B1D0-CC54757FAE0D.xml" role="parent"><?ditaot usertext?><linktext class="- topic/linktext "><?ditaot usertext?>User task</linktext></link></linkpool></related-links>
</task>