<?xml version="1.0" encoding="UTF-8"?><?ish ishref="GUID-EC737B8A-5349-48CA-9A78-9A4D1E5318A9" version="1" lang="en-US"?><tsTroubleshooting xmlns:ditaarch="http://dita.oasis-open.org/architecture/2005/" id="GUID-EC737B8A-5349-48CA-9A78-9A4D1E5318A9" xml:lang="en-US" ditaarch:DITAArchVersion="1.2" domains="(topic tsTroubleshooting)                            (topic hi-d)    (topic sdlVariables-c)                             (topic ut-d)                             (topic indexing-d)                            (topic sw-d)                            (topic ui-d)                            (topic oce-d)                            (topic oceCommonElements-c)                            (topic oceTopic-c hi-d oceHighlight-c)                            (topic oceTopic-c ui-d oceUi-c)                            (topic oceTopic-c sw-d oceSoftware-c)                            (topic oceTopic-c)                            (topic oceTopic-c task oceTask-c)                            (topic oceTopic-c tsTroubleshooting oceTroubleshooting-c)   " class="- topic/topic tsTroubleshooting/tsTroubleshooting "><title translate="no" class="- topic/title ">21581 TFTP connection to controller failed</title><abstract class="- topic/abstract " id="GUID-B87BF88B-91B2-4C27-A55C-91B9B6986C8A"><p class="- topic/p ">TFTP connection to controller failed. 
</p><p class="- topic/p ">There was a problem with the TFTP connection to the Windows controller. 
</p></abstract><prolog class="- topic/prolog "><metadata class="- topic/metadata "><category class="- topic/category ">Diagnostics</category></metadata></prolog><tsBody class="- topic/body tsTroubleshooting/tsBody "><tsSymptoms id="GUID-33E1B64A-E818-4500-A780-C8BC692D14B2" class="- topic/section tsTroubleshooting/tsSymptoms "><p class="- topic/p "> 
</p></tsSymptoms><tsCauses id="TSCAUSES_6C710CA8494E4E38989EB36E46D6247C" class="- topic/section tsTroubleshooting/tsCauses "><p class="- topic/p ">Restart the system/ Reinstall the system software 
</p></tsCauses><tsDiagnose id="TSDIAGNOSE_017EA4BBECA1459D9D68B740932B4B26" class="- topic/section tsTroubleshooting/tsDiagnose "><ol class="- topic/ol "><li class="- topic/li "><p class="- topic/p ">Power the printer OFF and back ON 
</p></li><li class="- topic/li "><p class="- topic/p "> Perform a 'Create backup' again. 
</p><p class="- topic/p "> In Settings Editor, browse to: "Support &gt; Backups &gt; Create backup" 
</p></li><li class="- topic/li "><p class="- topic/p "> If the issue remains, reinstall the system software. 
</p><p class="- topic/p ">See : 
<xref keyref="SystemSoftware" class="- topic/xref " href="GUID-CE050AF8-D3B9-42B7-A2B2-E37E71460728.xml" format="dita" locktitle="yes" type="task"><?ditaot usertext?><?xm-replace_text How to install-reinstall-upgrade-downgrade the system software?>How to install-reinstall-upgrade-downgrade the system software</xref> 
</p></li></ol></tsDiagnose><tsResolve id="TSRESOLVE_85F37607434D462A9913051E8A8CAB52" class="- topic/section tsTroubleshooting/tsResolve "><table pgwide="1" id="TABLE_5973C0C9DE1344D79C6A0FB640CB53B5" class="- topic/table "><tgroup align="left" outputclass="suspect" cols="6" class="- topic/tgroup "><colspec colname="col1" colnum="1" colwidth="15*" class="- topic/colspec "/><colspec colname="col2" colnum="2" colwidth="25*" class="- topic/colspec "/><colspec colname="col3" colnum="3" colwidth="15*" class="- topic/colspec "/><colspec colname="col4" colnum="4" colwidth="20*" class="- topic/colspec "/><colspec colname="col5" colnum="5" colwidth="10*" class="- topic/colspec "/><colspec colname="col6" colnum="6" colwidth="15*" class="- topic/colspec "/><thead valign="top" class="- topic/thead "><row class="- topic/row "><entry colname="col1" align="left" valign="top" class="- topic/entry "><p class="- topic/p ">Index 
</p></entry><entry colname="col2" align="left" valign="top" class="- topic/entry "><p class="- topic/p ">Description 
</p></entry><entry colname="col3" align="left" valign="top" class="- topic/entry "><p class="- topic/p ">Test 
</p></entry><entry colname="col4" align="left" valign="top" class="- topic/entry "><p class="- topic/p ">Action 
</p></entry><entry colname="col5" align="left" valign="top" class="- topic/entry "><p class="- topic/p ">Info 
</p></entry><entry colname="col6" align="left" valign="top" class="- topic/entry "><p class="- topic/p ">Diagram 
</p></entry></row></thead><tbody valign="top" class="- topic/tbody "><row class="- topic/row "><entry colname="col1" align="left" valign="top" class="- topic/entry "/><entry colname="col2" align="left" valign="top" class="- topic/entry "><p class="- topic/p "> Restart the printer 
</p></entry><entry colname="col3" align="left" valign="top" class="- topic/entry "/><entry colname="col4" align="left" valign="top" class="- topic/entry "><p class="- topic/p "> Power off/on 
</p></entry><entry colname="col5" align="left" valign="top" class="- topic/entry "/><entry colname="col6" align="left" valign="top" class="- topic/entry "/></row><row class="- topic/row "><entry colname="col1" align="left" valign="top" class="- topic/entry "/><entry colname="col2" align="left" valign="top" class="- topic/entry "><p class="- topic/p "> Create backup 
</p></entry><entry colname="col3" align="left" valign="top" class="- topic/entry "/><entry colname="col4" align="left" valign="top" class="- topic/entry "><p class="- topic/p "> In Settings Editor, browse to: 
</p><p class="- topic/p "> Support &gt; Backups &gt; Create backup 
</p></entry><entry colname="col5" align="left" valign="top" class="- topic/entry "/><entry colname="col6" align="left" valign="top" class="- topic/entry "/></row><row class="- topic/row "><entry colname="col1" align="left" valign="top" class="- topic/entry "/><entry colname="col2" align="left" valign="top" class="- topic/entry "><p class="- topic/p "> Re-install system software 
</p></entry><entry colname="col3" align="left" valign="top" class="- topic/entry "/><entry colname="col4" align="left" valign="top" class="- topic/entry "><p class="- topic/p ">Install software 
</p></entry><entry colname="col5" align="left" valign="top" class="- topic/entry "><p class="- topic/p "><xref keyref="SystemSoftware" class="- topic/xref " href="GUID-CE050AF8-D3B9-42B7-A2B2-E37E71460728.xml" format="dita" locktitle="yes" type="task"><?ditaot usertext?><?xm-replace_text How to install-reinstall-upgrade-downgrade the system software?>How to install-reinstall-upgrade-downgrade the system software</xref> 
</p></entry><entry colname="col6" align="left" valign="top" class="- topic/entry "/></row></tbody></tgroup></table></tsResolve></tsBody><related-links class="- topic/related-links "><linkpool class="- topic/linkpool " mapkeyref="GUID-8A41CFEA-5928-4042-A2CB-507A5D034160"><link class="- topic/link " mapclass="- map/topicref " format="dita" type="concept" href="generated-topic-GUID-1942788A-69CA-40A5-AECE-E8FDB08F0604.xml" role="parent"><?ditaot usertext?><linktext class="- topic/linktext "><?ditaot usertext?>Diagnostics</linktext></link></linkpool></related-links>
</tsTroubleshooting>